Workbook

Sheet Base
A1: Income | B1: Kidhome | C1: Teenhome | D1: Recency | E1: MntWines | F1: MntFruits | G1: MntMeatProducts | H1: MntFishProducts | I1: MntSweetProducts | J1: MntGoldProds | K1: NumDealsPurchases | L1: NumWebPurchases | M1: NumCatalogPurchases | N1: NumStorePurchases | O1: NumWebVisitsMonth | P1: AcceptedCmp3 | Q1: AcceptedCmp4 | R1: AcceptedCmp5 | S1: AcceptedCmp1 | T1: AcceptedCmp2 | U1: Complain | V1: Z_CostContact | W1: Z_Revenue | X1: Response | Y1: Age | Z1: Customer_Days | AA1: marital_Divorced | AB1: marital_Married | AC1: marital_Single | AD1: marital_Together | AE1: marital_Widow | AF1: education_2n Cycle | AG1: education_Basic | AH1: education_Graduation | AI1: education_Master | AJ1: education_PhD | AK1: MntTotal | AL1: MntRegularProds | AM1: AcceptedCmpOverall
A2: 58138.0 | B2: 0 | C2: 0 | D2: 58 | E2: 635 | F2: 88 | G2: 546 | H2: 172 | I2: 88 | J2: 88 | K2: 3 | L2: 8 | M2: 10 | N2: 4 | O2: 7 | P2: 0 | Q2: 0 | R2: 0 | S2: 0 | T2: 0 | U2: 0 | V2: 3 | W2: 11 | X2: 1 | Y2: 63 | Z2: 2822 | AA2: 0 | AB2: 0 | AC2: 1 | AD2: 0 | AE2: 0 | AF2: 0 | AG2: 0 | AH2: 1 | AI2: 0 | AJ2: 0 | AK2: 1529 | AL2: 1441 | AM2: 0
A3: 46344.0 | B3: 1 | C3: 1 | D3: 38 | E3: 11 | F3: 1 | G3: 6 | H3: 2 | I3: 1 | J3: 6 | K3: 2 | L3: 1 | M3: 1 | N3: 2 | O3: 5 | P3: 0 | Q3: 0 | R3: 0 | S3: 0 | T3: 0 | U3: 0 | V3: 3 | W3: 11 | X3: 0 | Y3: 66 | Z3: 2272 | AA3: 0 | AB3: 0 | AC3: 1 | AD3: 0 | AE3: 0 | AF3: 0 | AG3: 0 | AH3: 1 | AI3: 0 | AJ3: 0 | AK3: 21 | AL3: 15 | AM3: 0
A4: 71613.0 | B4: 0 | C4: 0 | D4: 26 | E4: 426 | F4: 49 | G4: 127 | H4: 111 | I4: 21 | J4: 42 | K4: 1 | L4: 8 | M4: 2 | N4: 10 | O4: 4 | P4: 0 | Q4: 0 | R4: 0 | S4: 0 | T4: 0 | U4: 0 | V4: 3 | W4: 11 | X4: 0 | Y4: 55 | Z4: 2471 | AA4: 0 | AB4: 0 | AC4: 0 | AD4: 1 | AE4: 0 | AF4: 0 | AG4: 0 | AH4: 1 | AI4: 0 | AJ4: 0 | AK4: 734 | AL4: 692 | AM4: 0
A5: 26646.0 | B5: 1 | C5: 0 | D5: 26 | E5: 11 | F5: 4 | G5: 20 | H5: 10 | I5: 3 | J5: 5 | K5: 2 | L5: 2 | M5: 0 | N5: 4 | O5: 6 | P5: 0 | Q5: 0 | R5: 0 | S5: 0 | T5: 0 | U5: 0 | V5: 3 | W5: 11 | X5: 0 | Y5: 36 | Z5: 2298 | AA5: 0 | AB5: 0 | AC5: 0 | AD5: 1 | AE5: 0 | AF5: 0 | AG5: 0 | AH5: 1 | AI5: 0 | AJ5: 0 | AK5: 48 | AL5: 43 | AM5: 0
A6: 58293.0 | B6: 1 | C6: 0 | D6: 94 | E6: 173 | F6: 43 | G6: 118 | H6: 46 | I6: 27 | J6: 15 | K6: 5 | L6: 5 | M6: 3 | N6: 6 | O6: 5 | P6: 0 | Q6: 0 | R6: 0 | S6: 0 | T6: 0 | U6: 0 | V6: 3 | W6: 11 | X6: 0 | Y6: 39 | Z6: 2320 | AA6: 0 | AB6: 1 | AC6: 0 | AD6: 0 | AE6: 0 | AF6: 0 | AG6: 0 | AH6: 0 | AI6: 0 | AJ6: 1 | AK6: 407 | AL6: 392 | AM6: 0
A7: 62513.0 | B7: 0 | C7: 1 | D7: 16 | E7: 520 | F7: 42 | G7: 98 | H7: 0 | I7: 42 | J7: 14 | K7: 2 | L7: 6 | M7: 4 | N7: 10 | O7: 6 | P7: 0 | Q7: 0 | R7: 0 | S7: 0 | T7: 0 | U7: 0 | V7: 3 | W7: 11 | X7: 0 | Y7: 53 | Z7: 2452 | AA7: 0 | AB7: 0 | AC7: 0 | AD7: 1 | AE7: 0 | AF7: 0 | AG7: 0 | AH7: 0 | AI7: 1 | AJ7: 0 | AK7: 702 | AL7: 688 | AM7: 0
A8: 55635.0 | B8: 0 | C8: 1 | D8: 34 | E8: 235 | F8: 65 | G8: 164 | H8: 50 | I8: 49 | J8: 27 | K8: 4 | L8: 7 | M8: 3 | N8: 7 | O8: 6 | P8: 0 | Q8: 0 | R8: 0 | S8: 0 | T8: 0 | U8: 0 | V8: 3 | W8: 11 | X8: 0 | Y8: 49 | Z8: 2752 | AA8: 1 | AB8: 0 | AC8: 0 | AD8: 0 | AE8: 0 | AF8: 0 | AG8: 0 | AH8: 1 | AI8: 0 | AJ8: 0 | AK8: 563 | AL8: 536 | AM8: 0
A9: 33454.0 | B9: 1 | C9: 0 | D9: 32 | E9: 76 | F9: 10 | G9: 56 | H9: 3 | I9: 1 | J9: 23 | K9: 2 | L9: 4 | M9: 0 | N9: 4 | O9: 8 | P9: 0 | Q9: 0 | R9: 0 | S9: 0 | T9: 0 | U9: 0 | V9: 3 | W9: 11 | X9: 0 | Y9: 35 | Z9: 2576 | AA9: 0 | AB9: 1 | AC9: 0 | AD9: 0 | AE9: 0 | AF9: 0 | AG9: 0 | AH9: 0 | AI9: 0 | AJ9: 1 | AK9: 146 | AL9: 123 | AM9: 0
A10: 30351.0 | B10: 1 | C10: 0 | D10: 19 | E10: 14 | F10: 0 | G10: 24 | H10: 3 | I10: 3 | J10: 2 | K10: 1 | L10: 3 | M10: 0 | N10: 2 | O10: 9 | P10: 0 | Q10: 0 | R10: 0 | S10: 0 | T10: 0 | U10: 0 | V10: 3 | W10: 11 | X10: 1 | Y10: 46 | Z10: 2547 | AA10: 0 | AB10: 0 | AC10: 0 | AD10: 1 | AE10: 0 | AF10: 0 | AG10: 0 | AH10: 0 | AI10: 0 | AJ10: 1 | AK10: 44 | AL10: 42 | AM10: 0
A11: 5648.0 | B11: 1 | C11: 1 | D11: 68 | E11: 28 | F11: 0 | G11: 6 | H11: 1 | I11: 1 | J11: 13 | K11: 1 | L11: 1 | M11: 0 | N11: 0 | O11: 20 | P11: 1 | Q11: 0 | R11: 0 | S11: 0 | T11: 0 | U11: 0 | V11: 3 | W11: 11 | X11: 0 | Y11: 70 | Z11: 2267 | AA11: 0 | AB11: 0 | AC11: 0 | AD11: 1 | AE11: 0 | AF11: 0 | AG11: 0 | AH11: 0 | AI11: 0 | AJ11: 1 | AK11: 36 | AL11: 23 | AM11: 1
A12: 7500.0 | B12: 0 | C12: 0 | D12: 59 | E12: 6 | F12: 16 | G12: 11 | H12: 11 | I12: 1 | J12: 16 | K12: 1 | L12: 2 | M12: 0 | N12: 3 | O12: 8 | P12: 0 | Q12: 0 | R12: 0 | S12: 0 | T12: 0 | U12: 0 | V12: 3 | W12: 11 | X12: 0 | Y12: 44 | Z12: 2752 | AA12: 0 | AB12: 1 | AC12: 0 | AD12: 0 | AE12: 0 | AF12: 0 | AG12: 1 | AH12: 0 | AI12: 0 | AJ12: 0 | AK12: 45 | AL12: 29 | AM12: 0
A13: 63033.0 | B13: 0 | C13: 0 | D13: 82 | E13: 194 | F13: 61 | G13: 480 | H13: 225 | I13: 112 | J13: 30 | K13: 1 | L13: 3 | M13: 4 | N13: 8 | O13: 2 | P13: 0 | Q13: 0 | R13: 0 | S13: 0 | T13: 0 | U13: 0 | V13: 3 | W13: 11 | X13: 0 | Y13: 61 | Z13: 2385 | AA13: 1 | AB13: 0 | AC13: 0 | AD13: 0 | AE13: 0 | AF13: 0 | AG13: 0 | AH13: 1 | AI13: 0 | AJ13: 0 | AK13: 1072 | AL13: 1042 | AM13: 0
... A2206: 52869.0 | B2206: 1 | C2206: 1 | D2206: 40 | E2206: 84 | F2206: 3 | G2206: 61 | H2206: 2 | I2206: 1 | J2206: 21 | K2206: 3 | L2206: 3 | M2206: 1 | N2206: 4 | O2206: 7 | P2206: 0 | Q2206: 0 | R2206: 0 | S2206: 0 | T2206: 0 | U2206: 0 | V2206: 3 | W2206: 11 | X2206: 1 | Y2206: 66 | Z2206: 2781 | AA2206: 0 | AB2206: 1 | AC2206: 0 | AD2206: 0 | AE2206: 0 | AF2206: 0 | AG2206: 0 | AH2206: 0 | AI2206: 0 | AJ2206: 1 | AK2206: 151 | AL2206: 130 | AM2206: 0

Sheet Base tratada
A1: ID | B1: Income | C1: Kidhome | D1: Teenhome | E1: Recency | F1: Faixa Recência | G1: Age | H1: Faixa Idade | I1: Customer_Days | J1: Estado Civil | K1: marital_Divorced | L1: marital_Married | M1: marital_Single | N1: marital_Together | O1: marital_Widow | P1: education_2n Cycle | Q1: education_Basic | R1: education_Graduation | S1: education_Master | T1: education_PhD | U1: MntWines | V1: MntFruits | W1: MntMeatProducts | X1: MntFishProducts | Y1: MntSweetProducts | Z1: MntGoldProds | AA1: NumDealsPurchases | AB1: NumWebVisitsMonth | AC1: NumWebPurchases | AD1: NumCatalogPurchases | AE1: NumStorePurchases | AF1: Total de Compras | AG1: Faixa Total de Compras | AH1: Canal Predominante | AI1: Ticket médio | AJ1: Faixa ticket médio | AK1: MntTotal | AL1: Faixa Gasto | AM1: AcceptedCmp1 | AN1: AcceptedCmp2 | AO1: AcceptedCmp3 | AP1: AcceptedCmp4 | AQ1: AcceptedCmp5 | AR1: AcceptedCmpOverall | AS1: Complain | AT1: Z_CostContact | AU1: Z_Revenue | AV1: MntRegularProds | AW1: Response | AX1: Categorização Response | AY1: Segmento | AZ1: Segmento Lucrativo
A2: 1 | B2: 58138 | C2: 0 | D2: 0 | E2: 58 | F2: =IF('Base tratada'!$E2<=15,"0-15 dias", IF('Base tratada'!$E2<=30, "16-30 dias", IF('Base tratada'!$E2<=45, "31-45 dias", IF('Base tratada'!$E2<=60, "46-60 dias", IF('Base tratada'!$E2<=75, "61-75 dias", "76-99 dias"))))) -> 46-60 dias | G2: 63 | H2: =IF('Base tratada'!$G2<=29,"24–29", IF('Base tratada'!$G2<=39,"30–39", IF('Base tratada'!$G2<=49,"40–49", IF('Base tratada'!$G2<=59,"50–59", IF('Base tratada'!$G2<=69,"60–69", "70–80"))))) -> 60–69 | I2: 2822 | J2: =IF('Base tratada'!$K2=1,"Divorciado", IF('Base tratada'!$L2=1,"Casado", IF('Base tratada'!$M2=1, "Solteiro", IF('Base tratada'!$N2=1,"Juntos", "Viúvo")))) -> Solteiro | K2: 0 | L2: 0 | M2: 1 | N2: 0 | O2: 0 | P2: 0 | Q2: 0 | R2: 1 | S2: 0 | T2: 0 | U2: 635 | V2: 88 | W2: 546 | X2: 172 | Y2: 88 | Z2: 88 | AA2: 3 | AB2: 7 | AC2: 8 | AD2: 10 | AE2: 4 | AF2: ='Base tratada'!$AC2+'Base tratada'!$AD2+'Base tratada'!$AE2 -> 22 | AG2: =IF(Tabela3[[#This Row],[Total de Compras]]=0,"0", IF(Tabela3[[#This Row],[Total de Compras]]<=4,"1–4", IF(Tabela3[[#This Row],[Total de Compras]]<=10,"5–10", IF(Tabela3[[#This Row],[Total de Compras]]<=15,"11–15", IF(Tabela3[[#This Row],[Total de Compras]]<=20,"16–20", "+20"))))) -> +20 | AH2: =IF('Base tratada'!$AC2>=MAX('Base tratada'!$AD2,'Base tratada'!$AE2),"Web", IF('Base tratada'!$AD2>='Base tratada'!$AE2,"Catalog", "Store")) -> Catalog | AI2: =IF('Base tratada'!$AF2=0,"0",'Base tratada'!$AK2/'Base tratada'!$AF2) -> 69.5 | AJ2: =IF('Base tratada'!$AI2=0,"R$ 0", IF('Base tratada'!$AI2<=25,"R$ 1–25", IF('Base tratada'!$AI2<=50,"R$ 26–50", "+R$ 50"))) -> +R$ 50 | AK2: 1529 | AL2: =IF('Base tratada'!$AK2<=100,"R$ 0-100", IF('Base tratada'!$AK2<=500,"R$ 101-500", IF('Base tratada'!$AK2<=1000,"R$ 501-1000", IF('Base tratada'!$AK2<=1500,"R$ 1001-1500", "+R$ 1500")))) -> +R$ 1500 | AM2: 0 | AN2: 0 | AO2: 0 | AP2: 0 | AQ2: 0 | AR2: 0 | AS2: 0 | AT2: 3 | AU2: 11 | AV2: 1441 | AW2: 1 | AX2: =IF(Tabela3[[#This Row],[Response]]=1, "Aceitou", "Não aceitou") -> Aceitou | AY2: =Tabela3[[#This Row],[Faixa Recência]] & " | " & Tabela3[[#This Row],[Faixa Gasto]] & " | " & Tabela3[[#This Row],[Faixa ticket médio]] -> 46-60 dias | +R$ 1500 | +R$ 50 | AZ2: =IF(OR( AND(Tabela3[[#This Row],[Recency]]<=30,Tabela3[[#This Row],[MntTotal]]>=1000,Tabela3[[#This Row],[MntTotal]]>=50), AND(AND(Tabela3[[#This Row],[Recency]]>30,Tabela3[[#This Row],[Recency]]<=45), OR(Tabela3[[#This Row],[MntTotal]]>=1500,Tabela3[[#This Row],[Ticket médio]]>=50)) ),"SIM","NÃO") -> NÃO
A3: 2 | B3: 46344 | C3: 1 | D3: 1 | E3: 38 | F3: =IF('Base tratada'!$E3<=15,"0-15 dias", IF('Base tratada'!$E3<=30, "16-30 dias", IF('Base tratada'!$E3<=45, "31-45 dias", IF('Base tratada'!$E3<=60, "46-60 dias", IF('Base tratada'!$E3<=75, "61-75 dias", "76-99 dias"))))) -> 31-45 dias | G3: 66 | H3: =IF('Base tratada'!$G3<=29,"24–29", IF('Base tratada'!$G3<=39,"30–39", IF('Base tratada'!$G3<=49,"40–49", IF('Base tratada'!$G3<=59,"50–59", IF('Base tratada'!$G3<=69,"60–69", "70–80"))))) -> 60–69 | I3: 2272 | J3: =IF('Base tratada'!$K3=1,"Divorciado", IF('Base tratada'!$L3=1,"Casado", IF('Base tratada'!$M3=1, "Solteiro", IF('Base tratada'!$N3=1,"Juntos", "Viúvo")))) -> Solteiro | K3: 0 | L3: 0 | M3: 1 | N3: 0 | O3: 0 | P3: 0 | Q3: 0 | R3: 1 | S3: 0 | T3: 0 | U3: 11 | V3: 1 | W3: 6 | X3: 2 | Y3: 1 | Z3: 6 | AA3: 2 | AB3: 5 | AC3: 1 | AD3: 1 | AE3: 2 | AF3: ='Base tratada'!$AC3+'Base tratada'!$AD3+'Base tratada'!$AE3 -> 4 | AG3: =IF(Tabela3[[#This Row],[Total de Compras]]=0,"0", IF(Tabela3[[#This Row],[Total de Compras]]<=4,"1–4", IF(Tabela3[[#This Row],[Total de Compras]]<=10,"5–10", IF(Tabela3[[#This Row],[Total de Compras]]<=15,"11–15", IF(Tabela3[[#This Row],[Total de Compras]]<=20,"16–20", "+20"))))) -> 1–4 | AH3: =IF('Base tratada'!$AC3>=MAX('Base tratada'!$AD3,'Base tratada'!$AE3),"Web", IF('Base tratada'!$AD3>='Base tratada'!$AE3,"Catalog", "Store")) -> Store | AI3: =IF('Base tratada'!$AF3=0,"0",'Base tratada'!$AK3/'Base tratada'!$AF3) -> 5.25 | AJ3: =IF('Base tratada'!$AI3=0,"R$ 0", IF('Base tratada'!$AI3<=25,"R$ 1–25", IF('Base tratada'!$AI3<=50,"R$ 26–50", "+R$ 50"))) -> R$ 1–25 | AK3: 21 | AL3: =IF('Base tratada'!$AK3<=100,"R$ 0-100", IF('Base tratada'!$AK3<=500,"R$ 101-500", IF('Base tratada'!$AK3<=1000,"R$ 501-1000", IF('Base tratada'!$AK3<=1500,"R$ 1001-1500", "+R$ 1500")))) -> R$ 0-100 | AM3: 0 | AN3: 0 | AO3: 0 | AP3: 0 | AQ3: 0 | AR3: 0 | AS3: 0 | AT3: 3 | AU3: 11 | AV3: 15 | AW3: 0 | AX3: =IF(Tabela3[[#This Row],[Response]]=1, "Aceitou", "Não aceitou") -> Não aceitou | AY3: =Tabela3[[#This Row],[Faixa Recência]] & " | " & Tabela3[[#This Row],[Faixa Gasto]] & " | " & Tabela3[[#This Row],[Faixa ticket médio]] -> 31-45 dias | R$ 0-100 | R$ 1–25 | AZ3: =IF(OR( AND(Tabela3[[#This Row],[Recency]]<=30,Tabela3[[#This Row],[MntTotal]]>=1000,Tabela3[[#This Row],[MntTotal]]>=50), AND(AND(Tabela3[[#This Row],[Recency]]>30,Tabela3[[#This Row],[Recency]]<=45), OR(Tabela3[[#This Row],[MntTotal]]>=1500,Tabela3[[#This Row],[Ticket médio]]>=50)) ),"SIM","NÃO") -> NÃO
A4: 3 | B4: 71613 | C4: 0 | D4: 0 | E4: 26 | F4: =IF('Base tratada'!$E4<=15,"0-15 dias", IF('Base tratada'!$E4<=30, "16-30 dias", IF('Base tratada'!$E4<=45, "31-45 dias", IF('Base tratada'!$E4<=60, "46-60 dias", IF('Base tratada'!$E4<=75, "61-75 dias", "76-99 dias"))))) -> 16-30 dias | G4: 55 | H4: =IF('Base tratada'!$G4<=29,"24–29", IF('Base tratada'!$G4<=39,"30–39", IF('Base tratada'!$G4<=49,"40–49", IF('Base tratada'!$G4<=59,"50–59", IF('Base tratada'!$G4<=69,"60–69", "70–80"))))) -> 50–59 | I4: 2471 | J4: =IF('Base tratada'!$K4=1,"Divorciado", IF('Base tratada'!$L4=1,"Casado", IF('Base tratada'!$M4=1, "Solteiro", IF('Base tratada'!$N4=1,"Juntos", "Viúvo")))) -> Juntos | K4: 0 | L4: 0 | M4: 0 | N4: 1 | O4: 0 | P4: 0 | Q4: 0 | R4: 1 | S4: 0 | T4: 0 | U4: 426 | V4: 49 | W4: 127 | X4: 111 | Y4: 21 | Z4: 42 | AA4: 1 | AB4: 4 | AC4: 8 | AD4: 2 | AE4: 10 | AF4: ='Base tratada'!$AC4+'Base tratada'!$AD4+'Base tratada'!$AE4 -> 20 | AG4: =IF(Tabela3[[#This Row],[Total de Compras]]=0,"0", IF(Tabela3[[#This Row],[Total de Compras]]<=4,"1–4", IF(Tabela3[[#This Row],[Total de Compras]]<=10,"5–10", IF(Tabela3[[#This Row],[Total de Compras]]<=15,"11–15", IF(Tabela3[[#This Row],[Total de Compras]]<=20,"16–20", "+20"))))) -> 16–20 | AH4: =IF('Base tratada'!$AC4>=MAX('Base tratada'!$AD4,'Base tratada'!$AE4),"Web", IF('Base tratada'!$AD4>='Base tratada'!$AE4,"Catalog", "Store")) -> Store | AI4: =IF('Base tratada'!$AF4=0,"0",'Base tratada'!$AK4/'Base tratada'!$AF4) -> 36.7 | AJ4: =IF('Base tratada'!$AI4=0,"R$ 0", IF('Base tratada'!$AI4<=25,"R$ 1–25", IF('Base tratada'!$AI4<=50,"R$ 26–50", "+R$ 50"))) -> R$ 26–50 | AK4: 734 | AL4: =IF('Base tratada'!$AK4<=100,"R$ 0-100", IF('Base tratada'!$AK4<=500,"R$ 101-500", IF('Base tratada'!$AK4<=1000,"R$ 501-1000", IF('Base tratada'!$AK4<=1500,"R$ 1001-1500", "+R$ 1500")))) -> R$ 501-1000 | AM4: 0 | AN4: 0 | AO4: 0 | AP4: 0 | AQ4: 0 | AR4: 0 | AS4: 0 | AT4: 3 | AU4: 11 | AV4: 692 | AW4: 0 | AX4: =IF(Tabela3[[#This Row],[Response]]=1, "Aceitou", "Não aceitou") -> Não aceitou | AY4: =Tabela3[[#This Row],[Faixa Recência]] & " | " & Tabela3[[#This Row],[Faixa Gasto]] & " | " & Tabela3[[#This Row],[Faixa ticket médio]] -> 16-30 dias | R$ 501-1000 | R$ 26–50 | AZ4: =IF(OR( AND(Tabela3[[#This Row],[Recency]]<=30,Tabela3[[#This Row],[MntTotal]]>=1000,Tabela3[[#This Row],[MntTotal]]>=50), AND(AND(Tabela3[[#This Row],[Recency]]>30,Tabela3[[#This Row],[Recency]]<=45), OR(Tabela3[[#This Row],[MntTotal]]>=1500,Tabela3[[#This Row],[Ticket médio]]>=50)) ),"SIM","NÃO") -> NÃO
A5: 4 | B5: 26646 | C5: 1 | D5: 0 | E5: 26 | F5: =IF('Base tratada'!$E5<=15,"0-15 dias", IF('Base tratada'!$E5<=30, "16-30 dias", IF('Base tratada'!$E5<=45, "31-45 dias", IF('Base tratada'!$E5<=60, "46-60 dias", IF('Base tratada'!$E5<=75, "61-75 dias", "76-99 dias"))))) -> 16-30 dias | G5: 36 | H5: =IF('Base tratada'!$G5<=29,"24–29", IF('Base tratada'!$G5<=39,"30–39", IF('Base tratada'!$G5<=49,"40–49", IF('Base tratada'!$G5<=59,"50–59", IF('Base tratada'!$G5<=69,"60–69", "70–80"))))) -> 30–39 | I5: 2298 | J5: =IF('Base tratada'!$K5=1,"Divorciado", IF('Base tratada'!$L5=1,"Casado", IF('Base tratada'!$M5=1, "Solteiro", IF('Base tratada'!$N5=1,"Juntos", "Viúvo")))) -> Juntos | K5: 0 | L5: 0 | M5: 0 | N5: 1 | O5: 0 | P5: 0 | Q5: 0 | R5: 1 | S5: 0 | T5: 0 | U5: 11 | V5: 4 | W5: 20 | X5: 10 | Y5: 3 | Z5: 5 | AA5: 2 | AB5: 6 | AC5: 2 | AD5: 0 | AE5: 4 | AF5: ='Base tratada'!$AC5+'Base tratada'!$AD5+'Base tratada'!$AE5 -> 6 | AG5: =IF(Tabela3[[#This Row],[Total de Compras]]=0,"0", IF(Tabela3[[#This Row],[Total de Compras]]<=4,"1–4", IF(Tabela3[[#This Row],[Total de Compras]]<=10,"5–10", IF(Tabela3[[#This Row],[Total de Compras]]<=15,"11–15", IF(Tabela3[[#This Row],[Total de Compras]]<=20,"16–20", "+20"))))) -> 5–10 | AH5: =IF('Base tratada'!$AC5>=MAX('Base tratada'!$AD5,'Base tratada'!$AE5),"Web", IF('Base tratada'!$AD5>='Base tratada'!$AE5,"Catalog", "Store")) -> Store | AI5: =IF('Base tratada'!$AF5=0,"0",'Base tratada'!$AK5/'Base tratada'!$AF5) -> 8 | AJ5: =IF('Base tratada'!$AI5=0,"R$ 0", IF('Base tratada'!$AI5<=25,"R$ 1–25", IF('Base tratada'!$AI5<=50,"R$ 26–50", "+R$ 50"))) -> R$ 1–25 | AK5: 48 | AL5: =IF('Base tratada'!$AK5<=100,"R$ 0-100", IF('Base tratada'!$AK5<=500,"R$ 101-500", IF('Base tratada'!$AK5<=1000,"R$ 501-1000", IF('Base tratada'!$AK5<=1500,"R$ 1001-1500", "+R$ 1500")))) -> R$ 0-100 | AM5: 0 | AN5: 0 | AO5: 0 | AP5: 0 | AQ5: 0 | AR5: 0 | AS5: 0 | AT5: 3 | AU5: 11 | AV5: 43 | AW5: 0 | AX5: =IF(Tabela3[[#This Row],[Response]]=1, "Aceitou", "Não aceitou") -> Não aceitou | AY5: =Tabela3[[#This Row],[Faixa Recência]] & " | " & Tabela3[[#This Row],[Faixa Gasto]] & " | " & Tabela3[[#This Row],[Faixa ticket médio]] -> 16-30 dias | R$ 0-100 | R$ 1–25 | AZ5: =IF(OR( AND(Tabela3[[#This Row],[Recency]]<=30,Tabela3[[#This Row],[MntTotal]]>=1000,Tabela3[[#This Row],[MntTotal]]>=50), AND(AND(Tabela3[[#This Row],[Recency]]>30,Tabela3[[#This Row],[Recency]]<=45), OR(Tabela3[[#This Row],[MntTotal]]>=1500,Tabela3[[#This Row],[Ticket médio]]>=50)) ),"SIM","NÃO") -> NÃO
A6: 5 | B6: 58293 | C6: 1 | D6: 0 | E6: 94 | F6: =IF('Base tratada'!$E6<=15,"0-15 dias", IF('Base tratada'!$E6<=30, "16-30 dias", IF('Base tratada'!$E6<=45, "31-45 dias", IF('Base tratada'!$E6<=60, "46-60 dias", IF('Base tratada'!$E6<=75, "61-75 dias", "76-99 dias"))))) -> 76-99 dias | G6: 39 | H6: =IF('Base tratada'!$G6<=29,"24–29", IF('Base tratada'!$G6<=39,"30–39", IF('Base tratada'!$G6<=49,"40–49", IF('Base tratada'!$G6<=59,"50–59", IF('Base tratada'!$G6<=69,"60–69", "70–80"))))) -> 30–39 | I6: 2320 | J6: =IF('Base tratada'!$K6=1,"Divorciado", IF('Base tratada'!$L6=1,"Casado", IF('Base tratada'!$M6=1, "Solteiro", IF('Base tratada'!$N6=1,"Juntos", "Viúvo")))) -> Casado | K6: 0 | L6: 1 | M6: 0 | N6: 0 | O6: 0 | P6: 0 | Q6: 0 | R6: 0 | S6: 0 | T6: 1 | U6: 173 | V6: 43 | W6: 118 | X6: 46 | Y6: 27 | Z6: 15 | AA6: 5 | AB6: 5 | AC6: 5 | AD6: 3 | AE6: 6 | AF6: ='Base tratada'!$AC6+'Base tratada'!$AD6+'Base tratada'!$AE6 -> 14 | AG6: =IF(Tabela3[[#This Row],[Total de Compras]]=0,"0", IF(Tabela3[[#This Row],[Total de Compras]]<=4,"1–4", IF(Tabela3[[#This Row],[Total de Compras]]<=10,"5–10", IF(Tabela3[[#This Row],[Total de Compras]]<=15,"11–15", IF(Tabela3[[#This Row],[Total de Compras]]<=20,"16–20", "+20"))))) -> 11–15 | AH6: =IF('Base tratada'!$AC6>=MAX('Base tratada'!$AD6,'Base tratada'!$AE6),"Web", IF('Base tratada'!$AD6>='Base tratada'!$AE6,"Catalog", "Store")) -> Store | AI6: =IF('Base tratada'!$AF6=0,"0",'Base tratada'!$AK6/'Base tratada'!$AF6) -> 29.071429 | AJ6: =IF('Base tratada'!$AI6=0,"R$ 0", IF('Base tratada'!$AI6<=25,"R$ 1–25", IF('Base tratada'!$AI6<=50,"R$ 26–50", "+R$ 50"))) -> R$ 26–50 | AK6: 407 | AL6: =IF('Base tratada'!$AK6<=100,"R$ 0-100", IF('Base tratada'!$AK6<=500,"R$ 101-500", IF('Base tratada'!$AK6<=1000,"R$ 501-1000", IF('Base tratada'!$AK6<=1500,"R$ 1001-1500", "+R$ 1500")))) -> R$ 101-500 | AM6: 0 | AN6: 0 | AO6: 0 | AP6: 0 | AQ6: 0 | AR6: 0 | AS6: 0 | AT6: 3 | AU6: 11 | AV6: 392 | AW6: 0 | AX6: =IF(Tabela3[[#This Row],[Response]]=1, "Aceitou", "Não aceitou") -> Não aceitou | AY6: =Tabela3[[#This Row],[Faixa Recência]] & " | " & Tabela3[[#This Row],[Faixa Gasto]] & " | " & Tabela3[[#This Row],[Faixa ticket médio]] -> 76-99 dias | R$ 101-500 | R$ 26–50 | AZ6: =IF(OR( AND(Tabela3[[#This Row],[Recency]]<=30,Tabela3[[#This Row],[MntTotal]]>=1000,Tabela3[[#This Row],[MntTotal]]>=50), AND(AND(Tabela3[[#This Row],[Recency]]>30,Tabela3[[#This Row],[Recency]]<=45), OR(Tabela3[[#This Row],[MntTotal]]>=1500,Tabela3[[#This Row],[Ticket médio]]>=50)) ),"SIM","NÃO") -> NÃO
A7: 6 | B7: 62513 | C7: 0 | D7: 1 | E7: 16 | F7: =IF('Base tratada'!$E7<=15,"0-15 dias", IF('Base tratada'!$E7<=30, "16-30 dias", IF('Base tratada'!$E7<=45, "31-45 dias", IF('Base tratada'!$E7<=60, "46-60 dias", IF('Base tratada'!$E7<=75, "61-75 dias", "76-99 dias"))))) -> 16-30 dias | G7: 53 | H7: =IF('Base tratada'!$G7<=29,"24–29", IF('Base tratada'!$G7<=39,"30–39", IF('Base tratada'!$G7<=49,"40–49", IF('Base tratada'!$G7<=59,"50–59", IF('Base tratada'!$G7<=69,"60–69", "70–80"))))) -> 50–59 | I7: 2452 | J7: =IF('Base tratada'!$K7=1,"Divorciado", IF('Base tratada'!$L7=1,"Casado", IF('Base tratada'!$M7=1, "Solteiro", IF('Base tratada'!$N7=1,"Juntos", "Viúvo")))) -> Juntos | K7: 0 | L7: 0 | M7: 0 | N7: 1 | O7: 0 | P7: 0 | Q7: 0 | R7: 0 | S7: 1 | T7: 0 | U7: 520 | V7: 42 | W7: 98 | X7: 0 | Y7: 42 | Z7: 14 | AA7: 2 | AB7: 6 | AC7: 6 | AD7: 4 | AE7: 10 | AF7: ='Base tratada'!$AC7+'Base tratada'!$AD7+'Base tratada'!$AE7 -> 20 | AG7: =IF(Tabela3[[#This Row],[Total de Compras]]=0,"0", IF(Tabela3[[#This Row],[Total de Compras]]<=4,"1–4", IF(Tabela3[[#This Row],[Total de Compras]]<=10,"5–10", IF(Tabela3[[#This Row],[Total de Compras]]<=15,"11–15", IF(Tabela3[[#This Row],[Total de Compras]]<=20,"16–20", "+20"))))) -> 16–20 | AH7: =IF('Base tratada'!$AC7>=MAX('Base tratada'!$AD7,'Base tratada'!$AE7),"Web", IF('Base tratada'!$AD7>='Base tratada'!$AE7,"Catalog", "Store")) -> Store | AI7: =IF('Base tratada'!$AF7=0,"0",'Base tratada'!$AK7/'Base tratada'!$AF7) -> 35.1 | AJ7: =IF('Base tratada'!$AI7=0,"R$ 0", IF('Base tratada'!$AI7<=25,"R$ 1–25", IF('Base tratada'!$AI7<=50,"R$ 26–50", "+R$ 50"))) -> R$ 26–50 | AK7: 702 | AL7: =IF('Base tratada'!$AK7<=100,"R$ 0-100", IF('Base tratada'!$AK7<=500,"R$ 101-500", IF('Base tratada'!$AK7<=1000,"R$ 501-1000", IF('Base tratada'!$AK7<=1500,"R$ 1001-1500", "+R$ 1500")))) -> R$ 501-1000 | AM7: 0 | AN7: 0 | AO7: 0 | AP7: 0 | AQ7: 0 | AR7: 0 | AS7: 0 | AT7: 3 | AU7: 11 | AV7: 688 | AW7: 0 | AX7: =IF(Tabela3[[#This Row],[Response]]=1, "Aceitou", "Não aceitou") -> Não aceitou | AY7: =Tabela3[[#This Row],[Faixa Recência]] & " | " & Tabela3[[#This Row],[Faixa Gasto]] & " | " & Tabela3[[#This Row],[Faixa ticket médio]] -> 16-30 dias | R$ 501-1000 | R$ 26–50 | AZ7: =IF(OR( AND(Tabela3[[#This Row],[Recency]]<=30,Tabela3[[#This Row],[MntTotal]]>=1000,Tabela3[[#This Row],[MntTotal]]>=50), AND(AND(Tabela3[[#This Row],[Recency]]>30,Tabela3[[#This Row],[Recency]]<=45), OR(Tabela3[[#This Row],[MntTotal]]>=1500,Tabela3[[#This Row],[Ticket médio]]>=50)) ),"SIM","NÃO") -> NÃO
A8: 7 | B8: 55635 | C8: 0 | D8: 1 | E8: 34 | F8: =IF('Base tratada'!$E8<=15,"0-15 dias", IF('Base tratada'!$E8<=30, "16-30 dias", IF('Base tratada'!$E8<=45, "31-45 dias", IF('Base tratada'!$E8<=60, "46-60 dias", IF('Base tratada'!$E8<=75, "61-75 dias", "76-99 dias"))))) -> 31-45 dias | G8: 49 | H8: =IF('Base tratada'!$G8<=29,"24–29", IF('Base tratada'!$G8<=39,"30–39", IF('Base tratada'!$G8<=49,"40–49", IF('Base tratada'!$G8<=59,"50–59", IF('Base tratada'!$G8<=69,"60–69", "70–80"))))) -> 40–49 | I8: 2752 | J8: =IF('Base tratada'!$K8=1,"Divorciado", IF('Base tratada'!$L8=1,"Casado", IF('Base tratada'!$M8=1, "Solteiro", IF('Base tratada'!$N8=1,"Juntos", "Viúvo")))) -> Divorciado | K8: 1 | L8: 0 | M8: 0 | N8: 0 | O8: 0 | P8: 0 | Q8: 0 | R8: 1 | S8: 0 | T8: 0 | U8: 235 | V8: 65 | W8: 164 | X8: 50 | Y8: 49 | Z8: 27 | AA8: 4 | AB8: 6 | AC8: 7 | AD8: 3 | AE8: 7 | AF8: ='Base tratada'!$AC8+'Base tratada'!$AD8+'Base tratada'!$AE8 -> 17 | AG8: =IF(Tabela3[[#This Row],[Total de Compras]]=0,"0", IF(Tabela3[[#This Row],[Total de Compras]]<=4,"1–4", IF(Tabela3[[#This Row],[Total de Compras]]<=10,"5–10", IF(Tabela3[[#This Row],[Total de Compras]]<=15,"11–15", IF(Tabela3[[#This Row],[Total de Compras]]<=20,"16–20", "+20"))))) -> 16–20 | AH8: =IF('Base tratada'!$AC8>=MAX('Base tratada'!$AD8,'Base tratada'!$AE8),"Web", IF('Base tratada'!$AD8>='Base tratada'!$AE8,"Catalog", "Store")) -> Web | AI8: =IF('Base tratada'!$AF8=0,"0",'Base tratada'!$AK8/'Base tratada'!$AF8) -> 33.117647 | AJ8: =IF('Base tratada'!$AI8=0,"R$ 0", IF('Base tratada'!$AI8<=25,"R$ 1–25", IF('Base tratada'!$AI8<=50,"R$ 26–50", "+R$ 50"))) -> R$ 26–50 | AK8: 563 | AL8: =IF('Base tratada'!$AK8<=100,"R$ 0-100", IF('Base tratada'!$AK8<=500,"R$ 101-500", IF('Base tratada'!$AK8<=1000,"R$ 501-1000", IF('Base tratada'!$AK8<=1500,"R$ 1001-1500", "+R$ 1500")))) -> R$ 501-1000 | AM8: 0 | AN8: 0 | AO8: 0 | AP8: 0 | AQ8: 0 | AR8: 0 | AS8: 0 | AT8: 3 | AU8: 11 | AV8: 536 | AW8: 0 | AX8: =IF(Tabela3[[#This Row],[Response]]=1, "Aceitou", "Não aceitou") -> Não aceitou | AY8: =Tabela3[[#This Row],[Faixa Recência]] & " | " & Tabela3[[#This Row],[Faixa Gasto]] & " | " & Tabela3[[#This Row],[Faixa ticket médio]] -> 31-45 dias | R$ 501-1000 | R$ 26–50 | AZ8: =IF(OR( AND(Tabela3[[#This Row],[Recency]]<=30,Tabela3[[#This Row],[MntTotal]]>=1000,Tabela3[[#This Row],[MntTotal]]>=50), AND(AND(Tabela3[[#This Row],[Recency]]>30,Tabela3[[#This Row],[Recency]]<=45), OR(Tabela3[[#This Row],[MntTotal]]>=1500,Tabela3[[#This Row],[Ticket médio]]>=50)) ),"SIM","NÃO") -> NÃO | BC8: target
A9: 8 | B9: 33454 | C9: 1 | D9: 0 | E9: 32 | F9: =IF('Base tratada'!$E9<=15,"0-15 dias", IF('Base tratada'!$E9<=30, "16-30 dias", IF('Base tratada'!$E9<=45, "31-45 dias", IF('Base tratada'!$E9<=60, "46-60 dias", IF('Base tratada'!$E9<=75, "61-75 dias", "76-99 dias"))))) -> 31-45 dias | G9: 35 | H9: =IF('Base tratada'!$G9<=29,"24–29", IF('Base tratada'!$G9<=39,"30–39", IF('Base tratada'!$G9<=49,"40–49", IF('Base tratada'!$G9<=59,"50–59", IF('Base tratada'!$G9<=69,"60–69", "70–80"))))) -> 30–39 | I9: 2576 | J9: =IF('Base tratada'!$K9=1,"Divorciado", IF('Base tratada'!$L9=1,"Casado", IF('Base tratada'!$M9=1, "Solteiro", IF('Base tratada'!$N9=1,"Juntos", "Viúvo")))) -> Casado | K9: 0 | L9: 1 | M9: 0 | N9: 0 | O9: 0 | P9: 0 | Q9: 0 | R9: 0 | S9: 0 | T9: 1 | U9: 76 | V9: 10 | W9: 56 | X9: 3 | Y9: 1 | Z9: 23 | AA9: 2 | AB9: 8 | AC9: 4 | AD9: 0 | AE9: 4 | AF9: ='Base tratada'!$AC9+'Base tratada'!$AD9+'Base tratada'!$AE9 -> 8 | AG9: =IF(Tabela3[[#This Row],[Total de Compras]]=0,"0", IF(Tabela3[[#This Row],[Total de Compras]]<=4,"1–4", IF(Tabela3[[#This Row],[Total de Compras]]<=10,"5–10", IF(Tabela3[[#This Row],[Total de Compras]]<=15,"11–15", IF(Tabela3[[#This Row],[Total de Compras]]<=20,"16–20", "+20"))))) -> 5–10 | AH9: =IF('Base tratada'!$AC9>=MAX('Base tratada'!$AD9,'Base tratada'!$AE9),"Web", IF('Base tratada'!$AD9>='Base tratada'!$AE9,"Catalog", "Store")) -> Web | AI9: =IF('Base tratada'!$AF9=0,"0",'Base tratada'!$AK9/'Base tratada'!$AF9) -> 18.25 | AJ9: =IF('Base tratada'!$AI9=0,"R$ 0", IF('Base tratada'!$AI9<=25,"R$ 1–25", IF('Base tratada'!$AI9<=50,"R$ 26–50", "+R$ 50"))) -> R$ 1–25 | AK9: 146 | AL9: =IF('Base tratada'!$AK9<=100,"R$ 0-100", IF('Base tratada'!$AK9<=500,"R$ 101-500", IF('Base tratada'!$AK9<=1000,"R$ 501-1000", IF('Base tratada'!$AK9<=1500,"R$ 1001-1500", "+R$ 1500")))) -> R$ 101-500 | AM9: 0 | AN9: 0 | AO9: 0 | AP9: 0 | AQ9: 0 | AR9: 0 | AS9: 0 | AT9: 3 | AU9: 11 | AV9: 123 | AW9: 0 | AX9: =IF(Tabela3[[#This Row],[Response]]=1, "Aceitou", "Não aceitou") -> Não aceitou | AY9: =Tabela3[[#This Row],[Faixa Recência]] & " | " & Tabela3[[#This Row],[Faixa Gasto]] & " | " & Tabela3[[#This Row],[Faixa ticket médio]] -> 31-45 dias | R$ 101-500 | R$ 1–25 | AZ9: =IF(OR( AND(Tabela3[[#This Row],[Recency]]<=30,Tabela3[[#This Row],[MntTotal]]>=1000,Tabela3[[#This Row],[MntTotal]]>=50), AND(AND(Tabela3[[#This Row],[Recency]]>30,Tabela3[[#This Row],[Recency]]<=45), OR(Tabela3[[#This Row],[MntTotal]]>=1500,Tabela3[[#This Row],[Ticket médio]]>=50)) ),"SIM","NÃO") -> NÃO | BC9: colunas criadas
A10: 9 | B10: 30351 | C10: 1 | D10: 0 | E10: 19 | F10: =IF('Base tratada'!$E10<=15,"0-15 dias", IF('Base tratada'!$E10<=30, "16-30 dias", IF('Base tratada'!$E10<=45, "31-45 dias", IF('Base tratada'!$E10<=60, "46-60 dias", IF('Base tratada'!$E10<=75, "61-75 dias", "76-99 dias"))))) -> 16-30 dias | G10: 46 | H10: =IF('Base tratada'!$G10<=29,"24–29", IF('Base tratada'!$G10<=39,"30–39", IF('Base tratada'!$G10<=49,"40–49", IF('Base tratada'!$G10<=59,"50–59", IF('Base tratada'!$G10<=69,"60–69", "70–80"))))) -> 40–49 | I10: 2547 | J10: =IF('Base tratada'!$K10=1,"Divorciado", IF('Base tratada'!$L10=1,"Casado", IF('Base tratada'!$M10=1, "Solteiro", IF('Base tratada'!$N10=1,"Juntos", "Viúvo")))) -> Juntos | K10: 0 | L10: 0 | M10: 0 | N10: 1 | O10: 0 | P10: 0 | Q10: 0 | R10: 0 | S10: 0 | T10: 1 | U10: 14 | V10: 0 | W10: 24 | X10: 3 | Y10: 3 | Z10: 2 | AA10: 1 | AB10: 9 | AC10: 3 | AD10: 0 | AE10: 2 | AF10: ='Base tratada'!$AC10+'Base tratada'!$AD10+'Base tratada'!$AE10 -> 5 | AG10: =IF(Tabela3[[#This Row],[Total de Compras]]=0,"0", IF(Tabela3[[#This Row],[Total de Compras]]<=4,"1–4", IF(Tabela3[[#This Row],[Total de Compras]]<=10,"5–10", IF(Tabela3[[#This Row],[Total de Compras]]<=15,"11–15", IF(Tabela3[[#This Row],[Total de Compras]]<=20,"16–20", "+20"))))) -> 5–10 | AH10: =IF('Base tratada'!$AC10>=MAX('Base tratada'!$AD10,'Base tratada'!$AE10),"Web", IF('Base tratada'!$AD10>='Base tratada'!$AE10,"Catalog", "Store")) -> Web | AI10: =IF('Base tratada'!$AF10=0,"0",'Base tratada'!$AK10/'Base tratada'!$AF10) -> 8.8 | AJ10: =IF('Base tratada'!$AI10=0,"R$ 0", IF('Base tratada'!$AI10<=25,"R$ 1–25", IF('Base tratada'!$AI10<=50,"R$ 26–50", "+R$ 50"))) -> R$ 1–25 | AK10: 44 | AL10: =IF('Base tratada'!$AK10<=100,"R$ 0-100", IF('Base tratada'!$AK10<=500,"R$ 101-500", IF('Base tratada'!$AK10<=1000,"R$ 501-1000", IF('Base tratada'!$AK10<=1500,"R$ 1001-1500", "+R$ 1500")))) -> R$ 0-100 | AM10: 0 | AN10: 0 | AO10: 0 | AP10: 0 | AQ10: 0 | AR10: 0 | AS10: 0 | AT10: 3 | AU10: 11 | AV10: 42 | AW10: 1 | AX10: =IF(Tabela3[[#This Row],[Response]]=1, "Aceitou", "Não aceitou") -> Aceitou | AY10: =Tabela3[[#This Row],[Faixa Recência]] & " | " & Tabela3[[#This Row],[Faixa Gasto]] & " | " & Tabela3[[#This Row],[Faixa ticket médio]] -> 16-30 dias | R$ 0-100 | R$ 1–25 | AZ10: =IF(OR( AND(Tabela3[[#This Row],[Recency]]<=30,Tabela3[[#This Row],[MntTotal]]>=1000,Tabela3[[#This Row],[MntTotal]]>=50), AND(AND(Tabela3[[#This Row],[Recency]]>30,Tabela3[[#This Row],[Recency]]<=45), OR(Tabela3[[#This Row],[MntTotal]]>=1500,Tabela3[[#This Row],[Ticket médio]]>=50)) ),"SIM","NÃO") -> NÃO | BC10: variável de segmentação
A11: 10 | B11: 5648 | C11: 1 | D11: 1 | E11: 68 | F11: =IF('Base tratada'!$E11<=15,"0-15 dias", IF('Base tratada'!$E11<=30, "16-30 dias", IF('Base tratada'!$E11<=45, "31-45 dias", IF('Base tratada'!$E11<=60, "46-60 dias", IF('Base tratada'!$E11<=75, "61-75 dias", "76-99 dias"))))) -> 61-75 dias | G11: 70 | H11: =IF('Base tratada'!$G11<=29,"24–29", IF('Base tratada'!$G11<=39,"30–39", IF('Base tratada'!$G11<=49,"40–49", IF('Base tratada'!$G11<=59,"50–59", IF('Base tratada'!$G11<=69,"60–69", "70–80"))))) -> 70–80 | I11: 2267 | J11: =IF('Base tratada'!$K11=1,"Divorciado", IF('Base tratada'!$L11=1,"Casado", IF('Base tratada'!$M11=1, "Solteiro", IF('Base tratada'!$N11=1,"Juntos", "Viúvo")))) -> Juntos | K11: 0 | L11: 0 | M11: 0 | N11: 1 | O11: 0 | P11: 0 | Q11: 0 | R11: 0 | S11: 0 | T11: 1 | U11: 28 | V11: 0 | W11: 6 | X11: 1 | Y11: 1 | Z11: 13 | AA11: 1 | AB11: 20 | AC11: 1 | AD11: 0 | AE11: 0 | AF11: ='Base tratada'!$AC11+'Base tratada'!$AD11+'Base tratada'!$AE11 -> 1 | AG11: =IF(Tabela3[[#This Row],[Total de Compras]]=0,"0", IF(Tabela3[[#This Row],[Total de Compras]]<=4,"1–4", IF(Tabela3[[#This Row],[Total de Compras]]<=10,"5–10", IF(Tabela3[[#This Row],[Total de Compras]]<=15,"11–15", IF(Tabela3[[#This Row],[Total de Compras]]<=20,"16–20", "+20"))))) -> 1–4 | AH11: =IF('Base tratada'!$AC11>=MAX('Base tratada'!$AD11,'Base tratada'!$AE11),"Web", IF('Base tratada'!$AD11>='Base tratada'!$AE11,"Catalog", "Store")) -> Web | AI11: =IF('Base tratada'!$AF11=0,"0",'Base tratada'!$AK11/'Base tratada'!$AF11) -> 36 | AJ11: =IF('Base tratada'!$AI11=0,"R$ 0", IF('Base tratada'!$AI11<=25,"R$ 1–25", IF('Base tratada'!$AI11<=50,"R$ 26–50", "+R$ 50"))) -> R$ 26–50 | AK11: 36 | AL11: =IF('Base tratada'!$AK11<=100,"R$ 0-100", IF('Base tratada'!$AK11<=500,"R$ 101-500", IF('Base tratada'!$AK11<=1000,"R$ 501-1000", IF('Base tratada'!$AK11<=1500,"R$ 1001-1500", "+R$ 1500")))) -> R$ 0-100 | AM11: 0 | AN11: 0 | AO11: 1 | AP11: 0 | AQ11: 0 | AR11: 1 | AS11: 0 | AT11: 3 | AU11: 11 | AV11: 23 | AW11: 0 | AX11: =IF(Tabela3[[#This Row],[Response]]=1, "Aceitou", "Não aceitou") -> Não aceitou | AY11: =Tabela3[[#This Row],[Faixa Recência]] & " | " & Tabela3[[#This Row],[Faixa Gasto]] & " | " & Tabela3[[#This Row],[Faixa ticket médio]] -> 61-75 dias | R$ 0-100 | R$ 26–50 | AZ11: =IF(OR( AND(Tabela3[[#This Row],[Recency]]<=30,Tabela3[[#This Row],[MntTotal]]>=1000,Tabela3[[#This Row],[MntTotal]]>=50), AND(AND(Tabela3[[#This Row],[Recency]]>30,Tabela3[[#This Row],[Recency]]<=45), OR(Tabela3[[#This Row],[MntTotal]]>=1500,Tabela3[[#This Row],[Ticket médio]]>=50)) ),"SIM","NÃO") -> NÃO
A12: 11 | B12: 7500 | C12: 0 | D12: 0 | E12: 59 | F12: =IF('Base tratada'!$E12<=15,"0-15 dias", IF('Base tratada'!$E12<=30, "16-30 dias", IF('Base tratada'!$E12<=45, "31-45 dias", IF('Base tratada'!$E12<=60, "46-60 dias", IF('Base tratada'!$E12<=75, "61-75 dias", "76-99 dias"))))) -> 46-60 dias | G12: 44 | H12: =IF('Base tratada'!$G12<=29,"24–29", IF('Base tratada'!$G12<=39,"30–39", IF('Base tratada'!$G12<=49,"40–49", IF('Base tratada'!$G12<=59,"50–59", IF('Base tratada'!$G12<=69,"60–69", "70–80"))))) -> 40–49 | I12: 2752 | J12: =IF('Base tratada'!$K12=1,"Divorciado", IF('Base tratada'!$L12=1,"Casado", IF('Base tratada'!$M12=1, "Solteiro", IF('Base tratada'!$N12=1,"Juntos", "Viúvo")))) -> Casado | K12: 0 | L12: 1 | M12: 0 | N12: 0 | O12: 0 | P12: 0 | Q12: 1 | R12: 0 | S12: 0 | T12: 0 | U12: 6 | V12: 16 | W12: 11 | X12: 11 | Y12: 1 | Z12: 16 | AA12: 1 | AB12: 8 | AC12: 2 | AD12: 0 | AE12: 3 | AF12: ='Base tratada'!$AC12+'Base tratada'!$AD12+'Base tratada'!$AE12 -> 5 | AG12: =IF(Tabela3[[#This Row],[Total de Compras]]=0,"0", IF(Tabela3[[#This Row],[Total de Compras]]<=4,"1–4", IF(Tabela3[[#This Row],[Total de Compras]]<=10,"5–10", IF(Tabela3[[#This Row],[Total de Compras]]<=15,"11–15", IF(Tabela3[[#This Row],[Total de Compras]]<=20,"16–20", "+20"))))) -> 5–10 | AH12: =IF('Base tratada'!$AC12>=MAX('Base tratada'!$AD12,'Base tratada'!$AE12),"Web", IF('Base tratada'!$AD12>='Base tratada'!$AE12,"Catalog", "Store")) -> Store | AI12: =IF('Base tratada'!$AF12=0,"0",'Base tratada'!$AK12/'Base tratada'!$AF12) -> 9 | AJ12: =IF('Base tratada'!$AI12=0,"R$ 0", IF('Base tratada'!$AI12<=25,"R$ 1–25", IF('Base tratada'!$AI12<=50,"R$ 26–50", "+R$ 50"))) -> R$ 1–25 | AK12: 45 | AL12: =IF('Base tratada'!$AK12<=100,"R$ 0-100", IF('Base tratada'!$AK12<=500,"R$ 101-500", IF('Base tratada'!$AK12<=1000,"R$ 501-1000", IF('Base tratada'!$AK12<=1500,"R$ 1001-1500", "+R$ 1500")))) -> R$ 0-100 | AM12: 0 | AN12: 0 | AO12: 0 | AP12: 0 | AQ12: 0 | AR12: 0 | AS12: 0 | AT12: 3 | AU12: 11 | AV12: 29 | AW12: 0 | AX12: =IF(Tabela3[[#This Row],[Response]]=1, "Aceitou", "Não aceitou") -> Não aceitou | AY12: =Tabela3[[#This Row],[Faixa Recência]] & " | " & Tabela3[[#This Row],[Faixa Gasto]] & " | " & Tabela3[[#This Row],[Faixa ticket médio]] -> 46-60 dias | R$ 0-100 | R$ 1–25 | AZ12: =IF(OR( AND(Tabela3[[#This Row],[Recency]]<=30,Tabela3[[#This Row],[MntTotal]]>=1000,Tabela3[[#This Row],[MntTotal]]>=50), AND(AND(Tabela3[[#This Row],[Recency]]>30,Tabela3[[#This Row],[Recency]]<=45), OR(Tabela3[[#This Row],[MntTotal]]>=1500,Tabela3[[#This Row],[Ticket médio]]>=50)) ),"SIM","NÃO") -> NÃO
A13: 12 | B13: 63033 | C13: 0 | D13: 0 | E13: 82 | F13: =IF('Base tratada'!$E13<=15,"0-15 dias", IF('Base tratada'!$E13<=30, "16-30 dias", IF('Base tratada'!$E13<=45, "31-45 dias", IF('Base tratada'!$E13<=60, "46-60 dias", IF('Base tratada'!$E13<=75, "61-75 dias", "76-99 dias"))))) -> 76-99 dias | G13: 61 | H13: =IF('Base tratada'!$G13<=29,"24–29", IF('Base tratada'!$G13<=39,"30–39", IF('Base tratada'!$G13<=49,"40–49", IF('Base tratada'!$G13<=59,"50–59", IF('Base tratada'!$G13<=69,"60–69", "70–80"))))) -> 60–69 | I13: 2385 | J13: =IF('Base tratada'!$K13=1,"Divorciado", IF('Base tratada'!$L13=1,"Casado", IF('Base tratada'!$M13=1, "Solteiro", IF('Base tratada'!$N13=1,"Juntos", "Viúvo")))) -> Divorciado | K13: 1 | L13: 0 | M13: 0 | N13: 0 | O13: 0 | P13: 0 | Q13: 0 | R13: 1 | S13: 0 | T13: 0 | U13: 194 | V13: 61 | W13: 480 | X13: 225 | Y13: 112 | Z13: 30 | AA13: 1 | AB13: 2 | AC13: 3 | AD13: 4 | AE13: 8 | AF13: ='Base tratada'!$AC13+'Base tratada'!$AD13+'Base tratada'!$AE13 -> 15 | AG13: =IF(Tabela3[[#This Row],[Total de Compras]]=0,"0", IF(Tabela3[[#This Row],[Total de Compras]]<=4,"1–4", IF(Tabela3[[#This Row],[Total de Compras]]<=10,"5–10", IF(Tabela3[[#This Row],[Total de Compras]]<=15,"11–15", IF(Tabela3[[#This Row],[Total de Compras]]<=20,"16–20", "+20"))))) -> 11–15 | AH13: =IF('Base tratada'!$AC13>=MAX('Base tratada'!$AD13,'Base tratada'!$AE13),"Web", IF('Base tratada'!$AD13>='Base tratada'!$AE13,"Catalog", "Store")) -> Store | AI13: =IF('Base tratada'!$AF13=0,"0",'Base tratada'!$AK13/'Base tratada'!$AF13) -> 71.466667 | AJ13: =IF('Base tratada'!$AI13=0,"R$ 0", IF('Base tratada'!$AI13<=25,"R$ 1–25", IF('Base tratada'!$AI13<=50,"R$ 26–50", "+R$ 50"))) -> +R$ 50 | AK13: 1072 | AL13: =IF('Base tratada'!$AK13<=100,"R$ 0-100", IF('Base tratada'!$AK13<=500,"R$ 101-500", IF('Base tratada'!$AK13<=1000,"R$ 501-1000", IF('Base tratada'!$AK13<=1500,"R$ 1001-1500", "+R$ 1500")))) -> R$ 1001-1500 | AM13: 0 | AN13: 0 | AO13: 0 | AP13: 0 | AQ13: 0 | AR13: 0 | AS13: 0 | AT13: 3 | AU13: 11 | AV13: 1042 | AW13: 0 | AX13: =IF(Tabela3[[#This Row],[Response]]=1, "Aceitou", "Não aceitou") -> Não aceitou | AY13: =Tabela3[[#This Row],[Faixa Recência]] & " | " & Tabela3[[#This Row],[Faixa Gasto]] & " | " & Tabela3[[#This Row],[Faixa ticket médio]] -> 76-99 dias | R$ 1001-1500 | +R$ 50 | AZ13: =IF(OR( AND(Tabela3[[#This Row],[Recency]]<=30,Tabela3[[#This Row],[MntTotal]]>=1000,Tabela3[[#This Row],[MntTotal]]>=50), AND(AND(Tabela3[[#This Row],[Recency]]>30,Tabela3[[#This Row],[Recency]]<=45), OR(Tabela3[[#This Row],[MntTotal]]>=1500,Tabela3[[#This Row],[Ticket médio]]>=50)) ),"SIM","NÃO") -> NÃO
A14: 13 | B14: 59354 | C14: 1 | D14: 1 | E14: 53 | F14: =IF('Base tratada'!$E14<=15,"0-15 dias", IF('Base tratada'!$E14<=30, "16-30 dias", IF('Base tratada'!$E14<=45, "31-45 dias", IF('Base tratada'!$E14<=60, "46-60 dias", IF('Base tratada'!$E14<=75, "61-75 dias", "76-99 dias"))))) -> 46-60 dias | G14: 68 | H14: =IF('Base tratada'!$G14<=29,"24–29", IF('Base tratada'!$G14<=39,"30–39", IF('Base tratada'!$G14<=49,"40–49", IF('Base tratada'!$G14<=59,"50–59", IF('Base tratada'!$G14<=69,"60–69", "70–80"))))) -> 60–69 | I14: 2385 | J14: =IF('Base tratada'!$K14=1,"Divorciado", IF('Base tratada'!$L14=1,"Casado", IF('Base tratada'!$M14=1, "Solteiro", IF('Base tratada'!$N14=1,"Juntos", "Viúvo")))) -> Divorciado | K14: 1 | L14: 0 | M14: 0 | N14: 0 | O14: 0 | P14: 0 | Q14: 0 | R14: 0 | S14: 1 | T14: 0 | U14: 233 | V14: 2 | W14: 53 | X14: 3 | Y14: 5 | Z14: 14 | AA14: 3 | AB14: 6 | AC14: 6 | AD14: 1 | AE14: 5 | AF14: ='Base tratada'!$AC14+'Base tratada'!$AD14+'Base tratada'!$AE14 -> 12 | AG14: =IF(Tabela3[[#This Row],[Total de Compras]]=0,"0", IF(Tabela3[[#This Row],[Total de Compras]]<=4,"1–4", IF(Tabela3[[#This Row],[Total de Compras]]<=10,"5–10", IF(Tabela3[[#This Row],[Total de Compras]]<=15,"11–15", IF(Tabela3[[#This Row],[Total de Compras]]<=20,"16–20", "+20"))))) -> 11–15 | AH14: =IF('Base tratada'!$AC14>=MAX('Base tratada'!$AD14,'Base tratada'!$AE14),"Web", IF('Base tratada'!$AD14>='Base tratada'!$AE14,"Catalog", "Store")) -> Web | AI14: =IF('Base tratada'!$AF14=0,"0",'Base tratada'!$AK14/'Base tratada'!$AF14) -> 24.666667 | AJ14: =IF('Base tratada'!$AI14=0,"R$ 0", IF('Base tratada'!$AI14<=25,"R$ 1–25", IF('Base tratada'!$AI14<=50,"R$ 26–50", "+R$ 50"))) -> R$ 1–25 | AK14: 296 | AL14: =IF('Base tratada'!$AK14<=100,"R$ 0-100", IF('Base tratada'!$AK14<=500,"R$ 101-500", IF('Base tratada'!$AK14<=1000,"R$ 501-1000", IF('Base tratada'!$AK14<=1500,"R$ 1001-1500", "+R$ 1500")))) -> R$ 101-500 | AM14: 0 | AN14: 0 | AO14: 0 | AP14: 0 | AQ14: 0 | AR14: 0 | AS14: 0 | AT14: 3 | AU14: 11 | AV14: 282 | AW14: 0 | AX14: =IF(Tabela3[[#This Row],[Response]]=1, "Aceitou", "Não aceitou") -> Não aceitou | AY14: =Tabela3[[#This Row],[Faixa Recência]] & " | " & Tabela3[[#This Row],[Faixa Gasto]] & " | " & Tabela3[[#This Row],[Faixa ticket médio]] -> 46-60 dias | R$ 101-500 | R$ 1–25 | AZ14: =IF(OR( AND(Tabela3[[#This Row],[Recency]]<=30,Tabela3[[#This Row],[MntTotal]]>=1000,Tabela3[[#This Row],[MntTotal]]>=50), AND(AND(Tabela3[[#This Row],[Recency]]>30,Tabela3[[#This Row],[Recency]]<=45), OR(Tabela3[[#This Row],[MntTotal]]>=1500,Tabela3[[#This Row],[Ticket médio]]>=50)) ),"SIM","NÃO") -> NÃO
A15: 14 | B15: 17323 | C15: 0 | D15: 0 | E15: 38 | F15: =IF('Base tratada'!$E15<=15,"0-15 dias", IF('Base tratada'!$E15<=30, "16-30 dias", IF('Base tratada'!$E15<=45, "31-45 dias", IF('Base tratada'!$E15<=60, "46-60 dias", IF('Base tratada'!$E15<=75, "61-75 dias", "76-99 dias"))))) -> 31-45 dias | G15: 33 | H15: =IF('Base tratada'!$G15<=29,"24–29", IF('Base tratada'!$G15<=39,"30–39", IF('Base tratada'!$G15<=49,"40–49", IF('Base tratada'!$G15<=59,"50–59", IF('Base tratada'!$G15<=69,"60–69", "70–80"))))) -> 30–39 | I15: 2786 | J15: =IF('Base tratada'!$K15=1,"Divorciado", IF('Base tratada'!$L15=1,"Casado", IF('Base tratada'!$M15=1, "Solteiro", IF('Base tratada'!$N15=1,"Juntos", "Viúvo")))) -> Casado | K15: 0 | L15: 1 | M15: 0 | N15: 0 | O15: 0 | P15: 0 | Q15: 0 | R15: 1 | S15: 0 | T15: 0 | U15: 3 | V15: 14 | W15: 17 | X15: 6 | Y15: 1 | Z15: 5 | AA15: 1 | AB15: 8 | AC15: 1 | AD15: 0 | AE15: 3 | AF15: ='Base tratada'!$AC15+'Base tratada'!$AD15+'Base tratada'!$AE15 -> 4 | AG15: =IF(Tabela3[[#This Row],[Total de Compras]]=0,"0", IF(Tabela3[[#This Row],[Total de Compras]]<=4,"1–4", IF(Tabela3[[#This Row],[Total de Compras]]<=10,"5–10", IF(Tabela3[[#This Row],[Total de Compras]]<=15,"11–15", IF(Tabela3[[#This Row],[Total de Compras]]<=20,"16–20", "+20"))))) -> 1–4 | AH15: =IF('Base tratada'!$AC15>=MAX('Base tratada'!$AD15,'Base tratada'!$AE15),"Web", IF('Base tratada'!$AD15>='Base tratada'!$AE15,"Catalog", "Store")) -> Store | AI15: =IF('Base tratada'!$AF15=0,"0",'Base tratada'!$AK15/'Base tratada'!$AF15) -> 10.25 | AJ15: =IF('Base tratada'!$AI15=0,"R$ 0", IF('Base tratada'!$AI15<=25,"R$ 1–25", IF('Base tratada'!$AI15<=50,"R$ 26–50", "+R$ 50"))) -> R$ 1–25 | AK15: 41 | AL15: =IF('Base tratada'!$AK15<=100,"R$ 0-100", IF('Base tratada'!$AK15<=500,"R$ 101-500", IF('Base tratada'!$AK15<=1000,"R$ 501-1000", IF('Base tratada'!$AK15<=1500,"R$ 1001-1500", "+R$ 1500")))) -> R$ 0-100 | AM15: 0 | AN15: 0 | AO15: 0 | AP15: 0 | AQ15: 0 | AR15: 0 | AS15: 0 | AT15: 3 | AU15: 11 | AV15: 36 | AW15: 0 | AX15: =IF(Tabela3[[#This Row],[Response]]=1, "Aceitou", "Não aceitou") -> Não aceitou | AY15: =Tabela3[[#This Row],[Faixa Recência]] & " | " & Tabela3[[#This Row],[Faixa Gasto]] & " | " & Tabela3[[#This Row],[Faixa ticket médio]] -> 31-45 dias | R$ 0-100 | R$ 1–25 | AZ15: =IF(OR( AND(Tabela3[[#This Row],[Recency]]<=30,Tabela3[[#This Row],[MntTotal]]>=1000,Tabela3[[#This Row],[MntTotal]]>=50), AND(AND(Tabela3[[#This Row],[Recency]]>30,Tabela3[[#This Row],[Recency]]<=45), OR(Tabela3[[#This Row],[MntTotal]]>=1500,Tabela3[[#This Row],[Ticket médio]]>=50)) ),"SIM","NÃO") -> NÃO
A16: 15 | B16: 82800 | C16: 0 | D16: 0 | E16: 23 | F16: =IF('Base tratada'!$E16<=15,"0-15 dias", IF('Base tratada'!$E16<=30, "16-30 dias", IF('Base tratada'!$E16<=45, "31-45 dias", IF('Base tratada'!$E16<=60, "46-60 dias", IF('Base tratada'!$E16<=75, "61-75 dias", "76-99 dias"))))) -> 16-30 dias | G16: 74 | H16: =IF('Base tratada'!$G16<=29,"24–29", IF('Base tratada'!$G16<=39,"30–39", IF('Base tratada'!$G16<=49,"40–49", IF('Base tratada'!$G16<=59,"50–59", IF('Base tratada'!$G16<=69,"60–69", "70–80"))))) -> 70–80 | I16: 2741 | J16: =IF('Base tratada'!$K16=1,"Divorciado", IF('Base tratada'!$L16=1,"Casado", IF('Base tratada'!$M16=1, "Solteiro", IF('Base tratada'!$N16=1,"Juntos", "Viúvo")))) -> Solteiro | K16: 0 | L16: 0 | M16: 1 | N16: 0 | O16: 0 | P16: 0 | Q16: 0 | R16: 0 | S16: 0 | T16: 1 | U16: 1006 | V16: 22 | W16: 115 | X16: 59 | Y16: 68 | Z16: 45 | AA16: 1 | AB16: 3 | AC16: 7 | AD16: 6 | AE16: 12 | AF16: ='Base tratada'!$AC16+'Base tratada'!$AD16+'Base tratada'!$AE16 -> 25 | AG16: =IF(Tabela3[[#This Row],[Total de Compras]]=0,"0", IF(Tabela3[[#This Row],[Total de Compras]]<=4,"1–4", IF(Tabela3[[#This Row],[Total de Compras]]<=10,"5–10", IF(Tabela3[[#This Row],[Total de Compras]]<=15,"11–15", IF(Tabela3[[#This Row],[Total de Compras]]<=20,"16–20", "+20"))))) -> +20 | AH16: =IF('Base tratada'!$AC16>=MAX('Base tratada'!$AD16,'Base tratada'!$AE16),"Web", IF('Base tratada'!$AD16>='Base tratada'!$AE16,"Catalog", "Store")) -> Store | AI16: =IF('Base tratada'!$AF16=0,"0",'Base tratada'!$AK16/'Base tratada'!$AF16) -> 50.8 | AJ16: =IF('Base tratada'!$AI16=0,"R$ 0", IF('Base tratada'!$AI16<=25,"R$ 1–25", IF('Base tratada'!$AI16<=50,"R$ 26–50", "+R$ 50"))) -> +R$ 50 | AK16: 1270 | AL16: =IF('Base tratada'!$AK16<=100,"R$ 0-100", IF('Base tratada'!$AK16<=500,"R$ 101-500", IF('Base tratada'!$AK16<=1000,"R$ 501-1000", IF('Base tratada'!$AK16<=1500,"R$ 1001-1500", "+R$ 1500")))) -> R$ 1001-1500 | AM16: 1 | AN16: 0 | AO16: 0 | AP16: 0 | AQ16: 1 | AR16: 2 | AS16: 0 | AT16: 3 | AU16: 11 | AV16: 1225 | AW16: 1 | AX16: =IF(Tabela3[[#This Row],[Response]]=1, "Aceitou", "Não aceitou") -> Aceitou | AY16: =Tabela3[[#This Row],[Faixa Recência]] & " | " & Tabela3[[#This Row],[Faixa Gasto]] & " | " & Tabela3[[#This Row],[Faixa ticket médio]] -> 16-30 dias | R$ 1001-1500 | +R$ 50 | AZ16: =IF(OR( AND(Tabela3[[#This Row],[Recency]]<=30,Tabela3[[#This Row],[MntTotal]]>=1000,Tabela3[[#This Row],[MntTotal]]>=50), AND(AND(Tabela3[[#This Row],[Recency]]>30,Tabela3[[#This Row],[Recency]]<=45), OR(Tabela3[[#This Row],[MntTotal]]>=1500,Tabela3[[#This Row],[Ticket médio]]>=50)) ),"SIM","NÃO") -> SIM
A17: 16 | B17: 41850 | C17: 1 | D17: 1 | E17: 51 | F17: =IF('Base tratada'!$E17<=15,"0-15 dias", IF('Base tratada'!$E17<=30, "16-30 dias", IF('Base tratada'!$E17<=45, "31-45 dias", IF('Base tratada'!$E17<=60, "46-60 dias", IF('Base tratada'!$E17<=75, "61-75 dias", "76-99 dias"))))) -> 46-60 dias | G17: 40 | H17: =IF('Base tratada'!$G17<=29,"24–29", IF('Base tratada'!$G17<=39,"30–39", IF('Base tratada'!$G17<=49,"40–49", IF('Base tratada'!$G17<=59,"50–59", IF('Base tratada'!$G17<=69,"60–69", "70–80"))))) -> 40–49 | I17: 2711 | J17: =IF('Base tratada'!$K17=1,"Divorciado", IF('Base tratada'!$L17=1,"Casado", IF('Base tratada'!$M17=1, "Solteiro", IF('Base tratada'!$N17=1,"Juntos", "Viúvo")))) -> Casado | K17: 0 | L17: 1 | M17: 0 | N17: 0 | O17: 0 | P17: 0 | Q17: 0 | R17: 1 | S17: 0 | T17: 0 | U17: 53 | V17: 5 | W17: 19 | X17: 2 | Y17: 13 | Z17: 4 | AA17: 3 | AB17: 8 | AC17: 3 | AD17: 0 | AE17: 3 | AF17: ='Base tratada'!$AC17+'Base tratada'!$AD17+'Base tratada'!$AE17 -> 6 | AG17: =IF(Tabela3[[#This Row],[Total de Compras]]=0,"0", IF(Tabela3[[#This Row],[Total de Compras]]<=4,"1–4", IF(Tabela3[[#This Row],[Total de Compras]]<=10,"5–10", IF(Tabela3[[#This Row],[Total de Compras]]<=15,"11–15", IF(Tabela3[[#This Row],[Total de Compras]]<=20,"16–20", "+20"))))) -> 5–10 | AH17: =IF('Base tratada'!$AC17>=MAX('Base tratada'!$AD17,'Base tratada'!$AE17),"Web", IF('Base tratada'!$AD17>='Base tratada'!$AE17,"Catalog", "Store")) -> Web | AI17: =IF('Base tratada'!$AF17=0,"0",'Base tratada'!$AK17/'Base tratada'!$AF17) -> 15.333333 | AJ17: =IF('Base tratada'!$AI17=0,"R$ 0", IF('Base tratada'!$AI17<=25,"R$ 1–25", IF('Base tratada'!$AI17<=50,"R$ 26–50", "+R$ 50"))) -> R$ 1–25 | AK17: 92 | AL17: =IF('Base tratada'!$AK17<=100,"R$ 0-100", IF('Base tratada'!$AK17<=500,"R$ 101-500", IF('Base tratada'!$AK17<=1000,"R$ 501-1000", IF('Base tratada'!$AK17<=1500,"R$ 1001-1500", "+R$ 1500")))) -> R$ 0-100 | AM17: 0 | AN17: 0 | AO17: 0 | AP17: 0 | AQ17: 0 | AR17: 0 | AS17: 0 | AT17: 3 | AU17: 11 | AV17: 88 | AW17: 0 | AX17: =IF(Tabela3[[#This Row],[Response]]=1, "Aceitou", "Não aceitou") -> Não aceitou | AY17: =Tabela3[[#This Row],[Faixa Recência]] & " | " & Tabela3[[#This Row],[Faixa Gasto]] & " | " & Tabela3[[#This Row],[Faixa ticket médio]] -> 46-60 dias | R$ 0-100 | R$ 1–25 | AZ17: =IF(OR( AND(Tabela3[[#This Row],[Recency]]<=30,Tabela3[[#This Row],[MntTotal]]>=1000,Tabela3[[#This Row],[MntTotal]]>=50), AND(AND(Tabela3[[#This Row],[Recency]]>30,Tabela3[[#This Row],[Recency]]<=45), OR(Tabela3[[#This Row],[MntTotal]]>=1500,Tabela3[[#This Row],[Ticket médio]]>=50)) ),"SIM","NÃO") -> NÃO
A18: 17 | B18: 37760 | C18: 0 | D18: 0 | E18: 20 | F18: =IF('Base tratada'!$E18<=15,"0-15 dias", IF('Base tratada'!$E18<=30, "16-30 dias", IF('Base tratada'!$E18<=45, "31-45 dias", IF('Base tratada'!$E18<=60, "46-60 dias", IF('Base tratada'!$E18<=75, "61-75 dias", "76-99 dias"))))) -> 16-30 dias | G18: 74 | H18: =IF('Base tratada'!$G18<=29,"24–29", IF('Base tratada'!$G18<=39,"30–39", IF('Base tratada'!$G18<=49,"40–49", IF('Base tratada'!$G18<=59,"50–59", IF('Base tratada'!$G18<=69,"60–69", "70–80"))))) -> 70–80 | I18: 2826 | J18: =IF('Base tratada'!$K18=1,"Divorciado", IF('Base tratada'!$L18=1,"Casado", IF('Base tratada'!$M18=1, "Solteiro", IF('Base tratada'!$N18=1,"Juntos", "Viúvo")))) -> Juntos | K18: 0 | L18: 0 | M18: 0 | N18: 1 | O18: 0 | P18: 0 | Q18: 0 | R18: 1 | S18: 0 | T18: 0 | U18: 84 | V18: 5 | W18: 38 | X18: 150 | Y18: 12 | Z18: 28 | AA18: 2 | AB18: 7 | AC18: 4 | AD18: 1 | AE18: 6 | AF18: ='Base tratada'!$AC18+'Base tratada'!$AD18+'Base tratada'!$AE18 -> 11 | AG18: =IF(Tabela3[[#This Row],[Total de Compras]]=0,"0", IF(Tabela3[[#This Row],[Total de Compras]]<=4,"1–4", IF(Tabela3[[#This Row],[Total de Compras]]<=10,"5–10", IF(Tabela3[[#This Row],[Total de Compras]]<=15,"11–15", IF(Tabela3[[#This Row],[Total de Compras]]<=20,"16–20", "+20"))))) -> 11–15 | AH18: =IF('Base tratada'!$AC18>=MAX('Base tratada'!$AD18,'Base tratada'!$AE18),"Web", IF('Base tratada'!$AD18>='Base tratada'!$AE18,"Catalog", "Store")) -> Store | AI18: =IF('Base tratada'!$AF18=0,"0",'Base tratada'!$AK18/'Base tratada'!$AF18) -> 26.272727 | AJ18: =IF('Base tratada'!$AI18=0,"R$ 0", IF('Base tratada'!$AI18<=25,"R$ 1–25", IF('Base tratada'!$AI18<=50,"R$ 26–50", "+R$ 50"))) -> R$ 26–50 | AK18: 289 | AL18: =IF('Base tratada'!$AK18<=100,"R$ 0-100", IF('Base tratada'!$AK18<=500,"R$ 101-500", IF('Base tratada'!$AK18<=1000,"R$ 501-1000", IF('Base tratada'!$AK18<=1500,"R$ 1001-1500", "+R$ 1500")))) -> R$ 101-500 | AM18: 0 | AN18: 0 | AO18: 0 | AP18: 0 | AQ18: 0 | AR18: 0 | AS18: 0 | AT18: 3 | AU18: 11 | AV18: 261 | AW18: 0 | AX18: =IF(Tabela3[[#This Row],[Response]]=1, "Aceitou", "Não aceitou") -> Não aceitou | AY18: =Tabela3[[#This Row],[Faixa Recência]] & " | " & Tabela3[[#This Row],[Faixa Gasto]] & " | " & Tabela3[[#This Row],[Faixa ticket médio]] -> 16-30 dias | R$ 101-500 | R$ 26–50 | AZ18: =IF(OR( AND(Tabela3[[#This Row],[Recency]]<=30,Tabela3[[#This Row],[MntTotal]]>=1000,Tabela3[[#This Row],[MntTotal]]>=50), AND(AND(Tabela3[[#This Row],[Recency]]>30,Tabela3[[#This Row],[Recency]]<=45), OR(Tabela3[[#This Row],[MntTotal]]>=1500,Tabela3[[#This Row],[Ticket médio]]>=50)) ),"SIM","NÃO") -> NÃO
A19: 18 | B19: 76995 | C19: 0 | D19: 1 | E19: 91 | F19: =IF('Base tratada'!$E19<=15,"0-15 dias", IF('Base tratada'!$E19<=30, "16-30 dias", IF('Base tratada'!$E19<=45, "31-45 dias", IF('Base tratada'!$E19<=60, "46-60 dias", IF('Base tratada'!$E19<=75, "61-75 dias", "76-99 dias"))))) -> 76-99 dias | G19: 71 | H19: =IF('Base tratada'!$G19<=29,"24–29", IF('Base tratada'!$G19<=39,"30–39", IF('Base tratada'!$G19<=49,"40–49", IF('Base tratada'!$G19<=59,"50–59", IF('Base tratada'!$G19<=69,"60–69", "70–80"))))) -> 70–80 | I19: 2617 | J19: =IF('Base tratada'!$K19=1,"Divorciado", IF('Base tratada'!$L19=1,"Casado", IF('Base tratada'!$M19=1, "Solteiro", IF('Base tratada'!$N19=1,"Juntos", "Viúvo")))) -> Casado | K19: 0 | L19: 1 | M19: 0 | N19: 0 | O19: 0 | P19: 0 | Q19: 0 | R19: 0 | S19: 1 | T19: 0 | U19: 1012 | V19: 80 | W19: 498 | X19: 0 | Y19: 16 | Z19: 176 | AA19: 2 | AB19: 5 | AC19: 11 | AD19: 4 | AE19: 9 | AF19: ='Base tratada'!$AC19+'Base tratada'!$AD19+'Base tratada'!$AE19 -> 24 | AG19: =IF(Tabela3[[#This Row],[Total de Compras]]=0,"0", IF(Tabela3[[#This Row],[Total de Compras]]<=4,"1–4", IF(Tabela3[[#This Row],[Total de Compras]]<=10,"5–10", IF(Tabela3[[#This Row],[Total de Compras]]<=15,"11–15", IF(Tabela3[[#This Row],[Total de Compras]]<=20,"16–20", "+20"))))) -> +20 | AH19: =IF('Base tratada'!$AC19>=MAX('Base tratada'!$AD19,'Base tratada'!$AE19),"Web", IF('Base tratada'!$AD19>='Base tratada'!$AE19,"Catalog", "Store")) -> Web | AI19: =IF('Base tratada'!$AF19=0,"0",'Base tratada'!$AK19/'Base tratada'!$AF19) -> 66.916667 | AJ19: =IF('Base tratada'!$AI19=0,"R$ 0", IF('Base tratada'!$AI19<=25,"R$ 1–25", IF('Base tratada'!$AI19<=50,"R$ 26–50", "+R$ 50"))) -> +R$ 50 | AK19: 1606 | AL19: =IF('Base tratada'!$AK19<=100,"R$ 0-100", IF('Base tratada'!$AK19<=500,"R$ 101-500", IF('Base tratada'!$AK19<=1000,"R$ 501-1000", IF('Base tratada'!$AK19<=1500,"R$ 1001-1500", "+R$ 1500")))) -> +R$ 1500 | AM19: 1 | AN19: 0 | AO19: 0 | AP19: 0 | AQ19: 0 | AR19: 1 | AS19: 0 | AT19: 3 | AU19: 11 | AV19: 1430 | AW19: 0 | AX19: =IF(Tabela3[[#This Row],[Response]]=1, "Aceitou", "Não aceitou") -> Não aceitou | AY19: =Tabela3[[#This Row],[Faixa Recência]] & " | " & Tabela3[[#This Row],[Faixa Gasto]] & " | " & Tabela3[[#This Row],[Faixa ticket médio]] -> 76-99 dias | +R$ 1500 | +R$ 50 | AZ19: =IF(OR( AND(Tabela3[[#This Row],[Recency]]<=30,Tabela3[[#This Row],[MntTotal]]>=1000,Tabela3[[#This Row],[MntTotal]]>=50), AND(AND(Tabela3[[#This Row],[Recency]]>30,Tabela3[[#This Row],[Recency]]<=45), OR(Tabela3[[#This Row],[MntTotal]]>=1500,Tabela3[[#This Row],[Ticket médio]]>=50)) ),"SIM","NÃO") -> NÃO
A20: 19 | B20: 33812 | C20: 1 | D20: 0 | E20: 86 | F20: =IF('Base tratada'!$E20<=15,"0-15 dias", IF('Base tratada'!$E20<=30, "16-30 dias", IF('Base tratada'!$E20<=45, "31-45 dias", IF('Base tratada'!$E20<=60, "46-60 dias", IF('Base tratada'!$E20<=75, "61-75 dias", "76-99 dias"))))) -> 76-99 dias | G20: 35 | H20: =IF('Base tratada'!$G20<=29,"24–29", IF('Base tratada'!$G20<=39,"30–39", IF('Base tratada'!$G20<=49,"40–49", IF('Base tratada'!$G20<=59,"50–59", IF('Base tratada'!$G20<=69,"60–69", "70–80"))))) -> 30–39 | I20: 2762 | J20: =IF('Base tratada'!$K20=1,"Divorciado", IF('Base tratada'!$L20=1,"Casado", IF('Base tratada'!$M20=1, "Solteiro", IF('Base tratada'!$N20=1,"Juntos", "Viúvo")))) -> Solteiro | K20: 0 | L20: 0 | M20: 1 | N20: 0 | O20: 0 | P20: 1 | Q20: 0 | R20: 0 | S20: 0 | T20: 0 | U20: 4 | V20: 17 | W20: 19 | X20: 30 | Y20: 24 | Z20: 39 | AA20: 2 | AB20: 6 | AC20: 2 | AD20: 1 | AE20: 3 | AF20: ='Base tratada'!$AC20+'Base tratada'!$AD20+'Base tratada'!$AE20 -> 6 | AG20: =IF(Tabela3[[#This Row],[Total de Compras]]=0,"0", IF(Tabela3[[#This Row],[Total de Compras]]<=4,"1–4", IF(Tabela3[[#This Row],[Total de Compras]]<=10,"5–10", IF(Tabela3[[#This Row],[Total de Compras]]<=15,"11–15", IF(Tabela3[[#This Row],[Total de Compras]]<=20,"16–20", "+20"))))) -> 5–10 | AH20: =IF('Base tratada'!$AC20>=MAX('Base tratada'!$AD20,'Base tratada'!$AE20),"Web", IF('Base tratada'!$AD20>='Base tratada'!$AE20,"Catalog", "Store")) -> Store | AI20: =IF('Base tratada'!$AF20=0,"0",'Base tratada'!$AK20/'Base tratada'!$AF20) -> 15.666667 | AJ20: =IF('Base tratada'!$AI20=0,"R$ 0", IF('Base tratada'!$AI20<=25,"R$ 1–25", IF('Base tratada'!$AI20<=50,"R$ 26–50", "+R$ 50"))) -> R$ 1–25 | AK20: 94 | AL20: =IF('Base tratada'!$AK20<=100,"R$ 0-100", IF('Base tratada'!$AK20<=500,"R$ 101-500", IF('Base tratada'!$AK20<=1000,"R$ 501-1000", IF('Base tratada'!$AK20<=1500,"R$ 1001-1500", "+R$ 1500")))) -> R$ 0-100 | AM20: 0 | AN20: 0 | AO20: 0 | AP20: 0 | AQ20: 0 | AR20: 0 | AS20: 0 | AT20: 3 | AU20: 11 | AV20: 55 | AW20: 0 | AX20: =IF(Tabela3[[#This Row],[Response]]=1, "Aceitou", "Não aceitou") -> Não aceitou | AY20: =Tabela3[[#This Row],[Faixa Recência]] & " | " & Tabela3[[#This Row],[Faixa Gasto]] & " | " & Tabela3[[#This Row],[Faixa ticket médio]] -> 76-99 dias | R$ 0-100 | R$ 1–25 | AZ20: =IF(OR( AND(Tabela3[[#This Row],[Recency]]<=30,Tabela3[[#This Row],[MntTotal]]>=1000,Tabela3[[#This Row],[MntTotal]]>=50), AND(AND(Tabela3[[#This Row],[Recency]]>30,Tabela3[[#This Row],[Recency]]<=45), OR(Tabela3[[#This Row],[MntTotal]]>=1500,Tabela3[[#This Row],[Ticket médio]]>=50)) ),"SIM","NÃO") -> NÃO
A21: 20 | B21: 37040 | C21: 0 | D21: 0 | E21: 41 | F21: =IF('Base tratada'!$E21<=15,"0-15 dias", IF('Base tratada'!$E21<=30, "16-30 dias", IF('Base tratada'!$E21<=45, "31-45 dias", IF('Base tratada'!$E21<=60, "46-60 dias", IF('Base tratada'!$E21<=75, "61-75 dias", "76-99 dias"))))) -> 31-45 dias | G21: 38 | H21: =IF('Base tratada'!$G21<=29,"24–29", IF('Base tratada'!$G21<=39,"30–39", IF('Base tratada'!$G21<=49,"40–49", IF('Base tratada'!$G21<=59,"50–59", IF('Base tratada'!$G21<=69,"60–69", "70–80"))))) -> 30–39 | I21: 2849 | J21: =IF('Base tratada'!$K21=1,"Divorciado", IF('Base tratada'!$L21=1,"Casado", IF('Base tratada'!$M21=1, "Solteiro", IF('Base tratada'!$N21=1,"Juntos", "Viúvo")))) -> Casado | K21: 0 | L21: 1 | M21: 0 | N21: 0 | O21: 0 | P21: 0 | Q21: 0 | R21: 1 | S21: 0 | T21: 0 | U21: 86 | V21: 2 | W21: 73 | X21: 69 | Y21: 38 | Z21: 48 | AA21: 1 | AB21: 8 | AC21: 4 | AD21: 2 | AE21: 5 | AF21: ='Base tratada'!$AC21+'Base tratada'!$AD21+'Base tratada'!$AE21 -> 11 | AG21: =IF(Tabela3[[#This Row],[Total de Compras]]=0,"0", IF(Tabela3[[#This Row],[Total de Compras]]<=4,"1–4", IF(Tabela3[[#This Row],[Total de Compras]]<=10,"5–10", IF(Tabela3[[#This Row],[Total de Compras]]<=15,"11–15", IF(Tabela3[[#This Row],[Total de Compras]]<=20,"16–20", "+20"))))) -> 11–15 | AH21: =IF('Base tratada'!$AC21>=MAX('Base tratada'!$AD21,'Base tratada'!$AE21),"Web", IF('Base tratada'!$AD21>='Base tratada'!$AE21,"Catalog", "Store")) -> Store | AI21: =IF('Base tratada'!$AF21=0,"0",'Base tratada'!$AK21/'Base tratada'!$AF21) -> 24.363636 | AJ21: =IF('Base tratada'!$AI21=0,"R$ 0", IF('Base tratada'!$AI21<=25,"R$ 1–25", IF('Base tratada'!$AI21<=50,"R$ 26–50", "+R$ 50"))) -> R$ 1–25 | AK21: 268 | AL21: =IF('Base tratada'!$AK21<=100,"R$ 0-100", IF('Base tratada'!$AK21<=500,"R$ 101-500", IF('Base tratada'!$AK21<=1000,"R$ 501-1000", IF('Base tratada'!$AK21<=1500,"R$ 1001-1500", "+R$ 1500")))) -> R$ 101-500 | AM21: 0 | AN21: 0 | AO21: 0 | AP21: 0 | AQ21: 0 | AR21: 0 | AS21: 0 | AT21: 3 | AU21: 11 | AV21: 220 | AW21: 0 | AX21: =IF(Tabela3[[#This Row],[Response]]=1, "Aceitou", "Não aceitou") -> Não aceitou | AY21: =Tabela3[[#This Row],[Faixa Recência]] & " | " & Tabela3[[#This Row],[Faixa Gasto]] & " | " & Tabela3[[#This Row],[Faixa ticket médio]] -> 31-45 dias | R$ 101-500 | R$ 1–25 | AZ21: =IF(OR( AND(Tabela3[[#This Row],[Recency]]<=30,Tabela3[[#This Row],[MntTotal]]>=1000,Tabela3[[#This Row],[MntTotal]]>=50), AND(AND(Tabela3[[#This Row],[Recency]]>30,Tabela3[[#This Row],[Recency]]<=45), OR(Tabela3[[#This Row],[MntTotal]]>=1500,Tabela3[[#This Row],[Ticket médio]]>=50)) ),"SIM","NÃO") -> NÃO
A22: 21 | B22: 2447 | C22: 1 | D22: 0 | E22: 42 | F22: =IF('Base tratada'!$E22<=15,"0-15 dias", IF('Base tratada'!$E22<=30, "16-30 dias", IF('Base tratada'!$E22<=45, "31-45 dias", IF('Base tratada'!$E22<=60, "46-60 dias", IF('Base tratada'!$E22<=75, "61-75 dias", "76-99 dias"))))) -> 31-45 dias | G22: 41 | H22: =IF('Base tratada'!$G22<=29,"24–29", IF('Base tratada'!$G22<=39,"30–39", IF('Base tratada'!$G22<=49,"40–49", IF('Base tratada'!$G22<=59,"50–59", IF('Base tratada'!$G22<=69,"60–69", "70–80"))))) -> 40–49 | I22: 2698 | J22: =IF('Base tratada'!$K22=1,"Divorciado", IF('Base tratada'!$L22=1,"Casado", IF('Base tratada'!$M22=1, "Solteiro", IF('Base tratada'!$N22=1,"Juntos", "Viúvo")))) -> Casado | K22: 0 | L22: 1 | M22: 0 | N22: 0 | O22: 0 | P22: 0 | Q22: 0 | R22: 1 | S22: 0 | T22: 0 | U22: 1 | V22: 1 | W22: 1725 | X22: 1 | Y22: 1 | Z22: 1 | AA22: 15 | AB22: 1 | AC22: 0 | AD22: 28 | AE22: 0 | AF22: ='Base tratada'!$AC22+'Base tratada'!$AD22+'Base tratada'!$AE22 -> 28 | AG22: =IF(Tabela3[[#This Row],[Total de Compras]]=0,"0", IF(Tabela3[[#This Row],[Total de Compras]]<=4,"1–4", IF(Tabela3[[#This Row],[Total de Compras]]<=10,"5–10", IF(Tabela3[[#This Row],[Total de Compras]]<=15,"11–15", IF(Tabela3[[#This Row],[Total de Compras]]<=20,"16–20", "+20"))))) -> +20 | AH22: =IF('Base tratada'!$AC22>=MAX('Base tratada'!$AD22,'Base tratada'!$AE22),"Web", IF('Base tratada'!$AD22>='Base tratada'!$AE22,"Catalog", "Store")) -> Catalog | AI22: =IF('Base tratada'!$AF22=0,"0",'Base tratada'!$AK22/'Base tratada'!$AF22) -> 61.75 | AJ22: =IF('Base tratada'!$AI22=0,"R$ 0", IF('Base tratada'!$AI22<=25,"R$ 1–25", IF('Base tratada'!$AI22<=50,"R$ 26–50", "+R$ 50"))) -> +R$ 50 | AK22: 1729 | AL22: =IF('Base tratada'!$AK22<=100,"R$ 0-100", IF('Base tratada'!$AK22<=500,"R$ 101-500", IF('Base tratada'!$AK22<=1000,"R$ 501-1000", IF('Base tratada'!$AK22<=1500,"R$ 1001-1500", "+R$ 1500")))) -> +R$ 1500 | AM22: 0 | AN22: 0 | AO22: 0 | AP22: 0 | AQ22: 0 | AR22: 0 | AS22: 0 | AT22: 3 | AU22: 11 | AV22: 1728 | AW22: 0 | AX22: =IF(Tabela3[[#This Row],[Response]]=1, "Aceitou", "Não aceitou") -> Não aceitou | AY22: =Tabela3[[#This Row],[Faixa Recência]] & " | " & Tabela3[[#This Row],[Faixa Gasto]] & " | " & Tabela3[[#This Row],[Faixa ticket médio]] -> 31-45 dias | +R$ 1500 | +R$ 50 | AZ22: =IF(OR( AND(Tabela3[[#This Row],[Recency]]<=30,Tabela3[[#This Row],[MntTotal]]>=1000,Tabela3[[#This Row],[MntTotal]]>=50), AND(AND(Tabela3[[#This Row],[Recency]]>30,Tabela3[[#This Row],[Recency]]<=45), OR(Tabela3[[#This Row],[MntTotal]]>=1500,Tabela3[[#This Row],[Ticket médio]]>=50)) ),"SIM","NÃO") -> SIM
... A2206: 2205 | B2206: 52869 | C2206: 1 | D2206: 1 | E2206: 40 | F2206: =IF('Base tratada'!$E2206<=15,"0-15 dias", IF('Base tratada'!$E2206<=30, "16-30 dias", IF('Base tratada'!$E2206<=45, "31-45 dias", IF('Base tratada'!$E2206<=60, "46-60 dias", IF('Base tratada'!$E2206<=75, "61-75 dias", "76-99 dias"))))) -> 31-45 dias | G2206: 66 | H2206: =IF('Base tratada'!$G2206<=29,"24–29", IF('Base tratada'!$G2206<=39,"30–39", IF('Base tratada'!$G2206<=49,"40–49", IF('Base tratada'!$G2206<=59,"50–59", IF('Base tratada'!$G2206<=69,"60–69", "70–80"))))) -> 60–69 | I2206: 2781 | J2206: =IF('Base tratada'!$K2206=1,"Divorciado", IF('Base tratada'!$L2206=1,"Casado", IF('Base tratada'!$M2206=1, "Solteiro", IF('Base tratada'!$N2206=1,"Juntos", "Viúvo")))) -> Casado | K2206: 0 | L2206: 1 | M2206: 0 | N2206: 0 | O2206: 0 | P2206: 0 | Q2206: 0 | R2206: 0 | S2206: 0 | T2206: 1 | U2206: 84 | V2206: 3 | W2206: 61 | X2206: 2 | Y2206: 1 | Z2206: 21 | AA2206: 3 | AB2206: 7 | AC2206: 3 | AD2206: 1 | AE2206: 4 | AF2206: ='Base tratada'!$AC2206+'Base tratada'!$AD2206+'Base tratada'!$AE2206 -> 8 | AG2206: =IF(Tabela3[[#This Row],[Total de Compras]]=0,"0", IF(Tabela3[[#This Row],[Total de Compras]]<=4,"1–4", IF(Tabela3[[#This Row],[Total de Compras]]<=10,"5–10", IF(Tabela3[[#This Row],[Total de Compras]]<=15,"11–15", IF(Tabela3[[#This Row],[Total de Compras]]<=20,"16–20", "+20"))))) -> 5–10 | AH2206: =IF('Base tratada'!$AC2206>=MAX('Base tratada'!$AD2206,'Base tratada'!$AE2206),"Web", IF('Base tratada'!$AD2206>='Base tratada'!$AE2206,"Catalog", "Store")) -> Store | AI2206: =IF('Base tratada'!$AF2206=0,"0",'Base tratada'!$AK2206/'Base tratada'!$AF2206) -> 18.875 | AJ2206: =IF('Base tratada'!$AI2206=0,"R$ 0", IF('Base tratada'!$AI2206<=25,"R$ 1–25", IF('Base tratada'!$AI2206<=50,"R$ 26–50", "+R$ 50"))) -> R$ 1–25 | AK2206: 151 | AL2206: =IF('Base tratada'!$AK2206<=100,"R$ 0-100", IF('Base tratada'!$AK2206<=500,"R$ 101-500", IF('Base tratada'!$AK2206<=1000,"R$ 501-1000", IF('Base tratada'!$AK2206<=1500,"R$ 1001-1500", "+R$ 1500")))) -> R$ 101-500 | AM2206: 0 | AN2206: 0 | AO2206: 0 | AP2206: 0 | AQ2206: 0 | AR2206: 0 | AS2206: 0 | AT2206: 3 | AU2206: 11 | AV2206: 130 | AW2206: 1 | AX2206: =IF(Tabela3[[#This Row],[Response]]=1, "Aceitou", "Não aceitou") -> Aceitou | AY2206: =Tabela3[[#This Row],[Faixa Recência]] & " | " & Tabela3[[#This Row],[Faixa Gasto]] & " | " & Tabela3[[#This Row],[Faixa ticket médio]] -> 31-45 dias | R$ 101-500 | R$ 1–25 | AZ2206: =IF(OR( AND(Tabela3[[#This Row],[Recency]]<=30,Tabela3[[#This Row],[MntTotal]]>=1000,Tabela3[[#This Row],[MntTotal]]>=50), AND(AND(Tabela3[[#This Row],[Recency]]>30,Tabela3[[#This Row],[Recency]]<=45), OR(Tabela3[[#This Row],[MntTotal]]>=1500,Tabela3[[#This Row],[Ticket médio]]>=50)) ),"SIM","NÃO") -> NÃO

Sheet EDA
A1: Análise Exploratória dos Dados (EDA)
A3: Recência (Recency) | B3: Freq. Relativa
A4: 0-15 dias | B4: 0.16689342
A5: 16-30 dias | B5: 0.1569161
A6: 31-45 dias | B6: 0.1292517
A7: 46-60 dias | B7: 0.16326531
A8: 61-75 dias | B8: 0.14739229
A9: 76-99 dias | B9: 0.23628118
A10: Total Geral | B10: 1
A13: Total Gasto (MnTotal) | B13: Freq. Relativa
A14: R$ 0-100 | B14: 0.34195011
A15: R$ 101-500 | B15: 0.23673469
A16: R$ 501-1000 | B16: 0.18367347
A17: R$ 1001-1500 | B17: 0.14829932
A18: +R$ 1500 | B18: 0.089342404
A19: Total Geral | B19: 1
A22: Canal de Compras | B22: Freq. Relativa
A23: Store | B23: 0.66122449
A24: Web | B24: 0.26848073
A25: Catalog | B25: 0.070294785
A26: Total Geral | B26: 1
A29: Idade (Age) | B29: Freq. Relativa
A30: 24–29 | B30: 0.019501134
A31: 30–39 | B31: 0.15238095
A32: 40–49 | B32: 0.31337868
A33: 50–59 | B33: 0.23945578
A34: 60–69 | B34: 0.21451247
A35: 70–80 | B35: 0.060770975
A36: Total Geral | B36: 1
A39: Estado Civil | B39: Freq. Relativa
A40: Casado | B40: 0.38730159
A41: Juntos | B41: 0.25759637
A42: Solteiro | B42: 0.21632653
A43: Divorciado | B43: 0.10430839
A44: Viúvo | B44: 0.03446712
A45: Total Geral | B45: 1
A48: Total Compras | B48: Freq. Relativa
A49: 1–4 | B49: 0.14947751
A50: 5–10 | B50: 0.29077692
A51: 11–15 | B51: 0.17900954
A52: 16–20 | B52: 0.20808723
A53: +20 | B53: 0.1726488
A54: Total Geral | B54: 1

Sheet Aplicação IV
A1: Aplicação do Método Estatístico (Information Value)
A3: Aceitação da Campanha | B3: Freq. Absoluta | C3: Freq. Relativa
A4: 0 | B4: 1872 | C4: 0.84897959 | N4: Variável | O4: IV | P4: Interpretação
A5: 1 | B5: 333 | C5: 0.15102041 | N5: Recência (dias) | O5: 0.336 | P5: Forte
A6: Total Geral | B6: 2205 | C6: 1 | N6: Idade | O6: 0.048 | P6: Fraca
N7: Estado Civil | O7: 0.17 | P7: Moderada
N8: Sensibilidade a Promoção | O8: 0.073 | P8: Fraca
B9: Aceitou a campanha? | N9: Total de Compras | O9: 0.24 | P9: Moderada
B10: 0 | D10: 1 | F10: Total Freq. Absoluta | G10: Total Freq. Relativa | N10: Canal Predominante | O10: 0.304 | P10: Forte
A11: Recência | B11: Freq. Absoluta | C11: Freq. Relativa | D11: Freq. Absoluta | E11: Freq. Relativa | H11: Aceitou (%) | I11: Odds | J11: IV | N11: Ticket Médio | O11: 0.35 | P11: Forte
A12: 0-15 dias | B12: 257 | C12: 0.13728632 | D12: 111 | E12: 0.33333333 | F12: 368 | G12: 0.16689342 | H12: =D12/F12 -> 0.30163043 | I12: =E12/C12 -> 2.4280156 | J12: =(E12-C12)*LN(I12) -> 0.17390826 | N12: Total Gasto Pelos Clientes | O12: 0.53 | P12: Forte
A13: 16-30 dias | B13: 284 | C13: 0.1517094 | D13: 62 | E13: 0.18618619 | F13: 346 | G13: 0.1569161 | H13: =D13/F13 -> 0.17919075 | I13: =E13/C13 -> 1.2272554 | J13: =(E13-C13)*LN(I13) -> 0.0070601667
A14: 31-45 dias | B14: 239 | C14: 0.12767094 | D14: 46 | E14: 0.13813814 | F14: 285 | G14: 0.1292517 | H14: =D14/F14 -> 0.16140351 | I14: =E14/C14 -> 1.0819858 | J14: =(E14-C14)*LN(I14) -> 0.00082479439
A15: 46-60 dias | B15: 317 | C15: 0.16933761 | D15: 43 | E15: 0.12912913 | F15: 360 | G15: 0.16326531 | H15: =D15/F15 -> 0.11944444 | I15: =E15/C15 -> 0.76255435 | J15: =(E15-C15)*LN(I15) -> 0.010899774
A16: 61-75 dias | B16: 292 | C16: 0.15598291 | D16: 33 | E16: 0.099099099 | F16: 325 | G16: 0.14739229 | H16: =D16/F16 -> 0.10153846 | I16: =E16/C16 -> 0.63532025 | J16: =(E16-C16)*LN(I16) -> 0.025803978
A17: 76-99 dias | B17: 483 | C17: 0.25801282 | D17: 38 | E17: 0.11411411 | F17: 521 | G17: 0.23628118 | H17: =D17/F17 -> 0.07293666 | I17: =E17/C17 -> 0.44228079 | J17: =(E17-C17)*LN(I17) -> 0.11739405
A18: Total Geral | B18: 1872 | C18: 1 | D18: 333 | E18: 1 | F18: 2205 | G18: 1 | H18: =D18/F18 -> 0.15102041 | J18: =SUM(J12:J17) -> 0.33589102
B21: Aceitou a campanha?
B22: 0 | D22: 1 | F22: Total Freq. Absoluta | G22: Total Freq. Relativa
A23: Idade | B23: Freq. Absoluta | C23: Freq. Relativa | D23: Freq. Absoluta | E23: Freq. Relativa | H23: Aceitou (%) | I23: Odds | J23: IV
A24: 24–29 | B24: 33 | C24: 0.017628205 | D24: 10 | E24: 0.03003003 | F24: 43 | G24: 0.019501134 | H24: =D24/F24 -> 0.23255814 | I24: =E24/C24 -> 1.7035217 | J24: =(E24-C24)*LN(I24) -> 0.0066064236
A25: 30–39 | B25: 270 | C25: 0.14423077 | D25: 66 | E25: 0.1981982 | F25: 336 | G25: 0.15238095 | H25: =D25/F25 -> 0.19642857 | I25: =E25/C25 -> 1.3741742 | J25: =(E25-C25)*LN(I25) -> 0.017153707
A26: 40–49 | B26: 597 | C26: 0.31891026 | D26: 94 | E26: 0.28228228 | F26: 691 | G26: 0.31337868 | H26: =D26/F26 -> 0.13603473 | I26: =E26/C26 -> 0.88514645 | J26: =(E26-C26)*LN(I26) -> 0.0044686921
A27: 50–59 | B27: 453 | C27: 0.24198718 | D27: 75 | E27: 0.22522523 | F27: 528 | G27: 0.23945578 | H27: =D27/F27 -> 0.14204545 | I27: =E27/C27 -> 0.93073206 | J27: =(E27-C27)*LN(I27) -> 0.0012032375
A28: 60–69 | B28: 413 | C28: 0.22061966 | D28: 60 | E28: 0.18018018 | F28: 473 | G28: 0.21451247 | H28: =D28/F28 -> 0.12684989 | I28: =E28/C28 -> 0.81670048 | J28: =(E28-C28)*LN(I28) -> 0.0081883013
A29: 70–80 | B29: 106 | C29: 0.056623932 | D29: 28 | E29: 0.084084084 | F29: 134 | G29: 0.060770975 | H29: =D29/F29 -> 0.20895522 | I29: =E29/C29 -> 1.4849567 | J29: =(E29-C29)*LN(I29) -> 0.010857348
A30: Total Geral | B30: 1872 | C30: 1 | D30: 333 | E30: 1 | F30: 2205 | G30: 1 | H30: =D30/F30 -> 0.15102041 | J30: =SUM(J24:J29) -> 0.048477709
B33: Aceitou a campanha?
B34: 0 | D34: 1 | F34: Total Freq. Absoluta | G34: Total Freq. Relativa
A35: Estado Civil | B35: Freq. Absoluta | C35: Freq. Relativa | D35: Freq. Absoluta | E35: Freq. Relativa | H35: Aceitou (%) | I35: Odds | J35: IV
A36: Casado | B36: 756 | C36: 0.40384615 | D36: 98 | E36: 0.29429429 | F36: 854 | G36: 0.38730159 | H36: =D36/F36 -> 0.1147541 | I36: =E36/C36 -> 0.72872873 | J36: =(E36-C36)*LN(I36) -> 0.034668095
A37: Divorciado | B37: 182 | C37: 0.097222222 | D37: 48 | E37: 0.14414414 | F37: 230 | G37: 0.10430839 | H37: =D37/F37 -> 0.20869565 | I37: =E37/C37 -> 1.4826255 | J37: =(E37-C37)*LN(I37) -> 0.018478533
A38: Juntos | B38: 508 | C38: 0.27136752 | D38: 60 | E38: 0.18018018 | F38: 568 | G38: 0.25759637 | H38: =D38/F38 -> 0.1056338 | I38: =E38/C38 -> 0.66397106 | J38: =(E38-C38)*LN(I38) -> 0.037342741
A39: Solteiro | B39: 368 | C39: 0.1965812 | D39: 109 | E39: 0.32732733 | F39: 477 | G39: 0.21632653 | H39: =D39/F39 -> 0.22851153 | I39: =E39/C39 -> 1.6650999 | J39: =(E39-C39)*LN(I39) -> 0.066665505
A40: Viúvo | B40: 58 | C40: 0.030982906 | D40: 18 | E40: 0.054054054 | F40: 76 | G40: 0.03446712 | H40: =D40/F40 -> 0.23684211 | I40: =E40/C40 -> 1.7446412 | J40: =(E40-C40)*LN(I40) -> 0.012840222
A41: Total Geral | B41: 1872 | C41: 1 | D41: 333 | E41: 1 | F41: 2205 | G41: 1 | H41: =D41/F41 -> 0.15102041 | J41: =SUM(J36:J40) -> 0.1699951
B44: Aceitou a campanha?
B45: 0 | D45: 1 | F45: Total Freq. Absoluta | G45: Total Freq. Relativa
A46: Total de Compras | B46: Freq. Absoluta | C46: Freq. Relativa | D46: Freq. Absoluta | E46: Freq. Relativa | H46: Aceitou (%) | I46: Odds | J46: IV
A47: 0 | B47: 4 | C47: 0.0021367521 | E47: 0 | F47: 4 | G47: 0.001814059 | H47: =D47/F47 -> 0 | I47: =E47/C47 -> 0 | J47: 0
A48: 1–4 | B48: 309 | C48: 0.1650641 | D48: 20 | E48: 0.06006006 | F48: 329 | G48: 0.14920635 | H48: =D48/F48 -> 0.060790274 | I48: =E48/C48 -> 0.363859 | J48: =(E48-C48)*LN(I48) -> 0.10615791
A49: 5–10 | B49: 574 | C49: 0.30662393 | D49: 66 | E49: 0.1981982 | F49: 640 | G49: 0.29024943 | H49: =D49/F49 -> 0.103125 | I49: =E49/C49 -> 0.64638855 | J49: =(E49-C49)*LN(I49) -> 0.047312055
A50: 11–15 | B50: 325 | C50: 0.17361111 | D50: 69 | E50: 0.20720721 | F50: 394 | G50: 0.17868481 | H50: =D50/F50 -> 0.1751269 | I50: =E50/C50 -> 1.1935135 | J50: =(E50-C50)*LN(I50) -> 0.0059431994
A51: 16–20 | B51: 364 | C51: 0.19444444 | D51: 94 | E51: 0.28228228 | F51: 458 | G51: 0.20770975 | H51: =D51/F51 -> 0.20524017 | I51: =E51/C51 -> 1.4517375 | J51: =(E51-C51)*LN(I51) -> 0.032742527
A52: +20 | B52: 296 | C52: 0.15811966 | D52: 84 | E52: 0.25225225 | F52: 380 | G52: 0.1723356 | H52: =D52/F52 -> 0.22105263 | I52: =E52/C52 -> 1.5953251 | J52: =(E52-C52)*LN(I52) -> 0.043967218
A53: Total Geral | B53: 1872 | C53: 1 | D53: 333 | E53: 1 | F53: 2205 | G53: 1 | H53: =D53/F53 -> 0.15102041 | J53: =SUM(J47:J52) -> 0.23612291
B56: Aceitou a campanha?
B57: 0 | D57: 1 | F57: Total Freq. Absoluta | G57: Total Freq. Relativa
A58: Canal Predominante | B58: Freq. Absoluta | C58: Freq. Relativa | D58: Freq. Absoluta | E58: Freq. Relativa | H58: Aceitou (%) | I58: Odds | J58: IV
A59: Store | B59: 1308 | C59: 0.69871795 | D59: 150 | E59: 0.45045045 | F59: 1458 | G59: 0.66122449 | H59: =D59/F59 -> 0.10288066 | I59: =E59/C59 -> 0.64468138 | J59: =(E59-C59)*LN(I59) -> 0.1089892
A60: Web | B60: 466 | C60: 0.24893162 | D60: 126 | E60: 0.37837838 | F60: 592 | G60: 0.26848073 | H60: =D60/F60 -> 0.21283784 | I60: =E60/C60 -> 1.5200093 | J60: =(E60-C60)*LN(I60) -> 0.054201484
A61: Catalog | B61: 98 | C61: 0.052350427 | D61: 57 | E61: 0.17117117 | F61: 155 | G61: 0.070294785 | H61: =D61/F61 -> 0.36774194 | I61: =E61/C61 -> 3.2697187 | J61: =(E61-C61)*LN(I61) -> 0.14076741
A62: Total Geral | B62: 1872 | C62: 1 | D62: 333 | E62: 1 | F62: 2205 | G62: 1 | H62: =D62/F62 -> 0.15102041 | J62: =SUM(J59:J61) -> 0.30395809
B66: Aceitou a campanha?
B67: 0 | D67: 1 | F67: Total Freq. Absoluta | G67: Total Freq. Relativa
A68: Ticket Médio | B68: Freq. Absoluta | C68: Freq. Relativa | D68: Freq. Absoluta | E68: Freq. Relativa | H68: Aceitou (%) | I68: Odds | J68: IV
A69: R$ 1–25 | B69: 948 | C69: 0.50641026 | D69: 99 | E69: 0.2972973 | F69: 1047 | G69: 0.47482993 | H69: =D69/F69 -> 0.094555874 | I69: =E69/C69 -> 0.58706808 | J69: =(E69-C69)*LN(I69) -> 0.11137659
A70: R$ 26–50 | B70: 544 | C70: 0.29059829 | D70: 77 | E70: 0.23123123 | F70: 621 | G70: 0.28163265 | H70: =D70/F70 -> 0.12399356 | I70: =E70/C70 -> 0.79570747 | J70: =(E70-C70)*LN(I70) -> 0.013566778
A71: +R$ 50 | B71: 380 | C71: 0.20299145 | D71: 157 | E71: 0.47147147 | F71: 537 | G71: 0.24353741 | H71: =D71/F71 -> 0.29236499 | I71: =E71/C71 -> 2.3226174 | J71: =(E71-C71)*LN(I71) -> 0.22624669
A72: Total Geral | B72: 1872 | C72: 1 | D72: 333 | E72: 1 | F72: 2205 | G72: 1 | H72: =D72/F72 -> 0.15102041 | I72: =E72/C72 -> 1 | J72: =SUM(J69:J71) -> 0.35119006
B77: Aceitou a campanha?
B78: 0 | D78: 1 | F78: Total Freq. Absoluta | G78: Total Freq. Relativa
A79: Total Gasto Pelo Cliente | B79: Freq. Absoluta | C79: Freq. Relativa | D79: Freq. Absoluta | E79: Freq. Relativa | H79: Aceitou (%) | I79: Odds | J79: IV
A80: R$ 0-100 | B80: 693 | C80: 0.37019231 | D80: 61 | E80: 0.18318318 | F80: 754 | G80: 0.34195011 | H80: =D80/F80 -> 0.080901857 | I80: =E80/C80 -> 0.49483249 | J80: =(E80-C80)*LN(I80) -> 0.13156765
A81: R$ 101-500 | B81: 455 | C81: 0.24305556 | D81: 67 | E81: 0.2012012 | F81: 522 | G81: 0.23673469 | H81: =D81/F81 -> 0.12835249 | I81: =E81/C81 -> 0.82779923 | J81: =(E81-C81)*LN(I81) -> 0.0079098298
A82: R$ 501-1000 | B82: 363 | C82: 0.19391026 | D82: 42 | E82: 0.12612613 | F82: 405 | G82: 0.18367347 | H82: =D82/F82 -> 0.1037037 | I82: =E82/C82 -> 0.65043556 | J82: =(E82-C82)*LN(I82) -> 0.029154839
A83: R$ 1001-1500 | B83: 253 | C83: 0.13514957 | D83: 74 | E83: 0.22222222 | F83: 327 | G83: 0.14829932 | H83: =D83/F83 -> 0.22629969 | I83: =E83/C83 -> 1.6442688 | J83: =(E83-C83)*LN(I83) -> 0.04330086
A84: +R$ 1500 | B84: 108 | C84: 0.057692308 | D84: 89 | E84: 0.26726727 | F84: 197 | G84: 0.089342404 | H84: =D84/F84 -> 0.45177665 | I84: =E84/C84 -> 4.6326326 | J84: =(E84-C84)*LN(I84) -> 0.32130467
A85: Total Geral | B85: 1872 | C85: 1 | D85: 333 | E85: 1 | F85: 2205 | G85: 1 | H85: =D85/F85 -> 0.15102041 | I85: =E85/C85 -> 1 | J85: =SUM(J80:J84) -> 0.53323785
H86: =D86/F86 -> #DIV/0!

Sheet Análises
A1: Análises + Insights Preliminares
A4: Aceitação da Campanha | B4: Freq. Absoluta | C4: Freq. Relativa
A5: 0 | B5: 1872 | C5: 0.84897959
A6: 1 | B6: 333 | C6: 0.15102041
A7: Total Geral | B7: 2205 | C7: 1
B10: Aceitou a campanha? | J10: Clientes com até 15 dias têm 30,2% de aceitação (2x a média geral de aceitação). Clientes com recência entre 16-45 dias têm aceitação próxima a média geral. A partir do 46 dia há uma queda consistente até 7.3%
B11: 0 | D11: 1 | F11: Total Freq. Absoluta | G11: Total Freq. Relativa | J11: Apresenta queda consistente conforme a recência aumenta.
A12: Recência (dias) | B12: Freq. Absoluta | C12: Freq. Relativa | D12: Freq. Absoluta | E12: Freq. Relativa | H12: Aceitação (%) | J12: A probabilidade de aceitação diminui significativamente à medida que o tempo desde a última compra aumenta.
A13: 0-15 dias | B13: 257 | C13: 0.13728632 | D13: 111 | E13: 0.33333333 | F13: 368 | G13: 0.16689342 | H13: =D13/F13 -> 0.30163043
A14: 16-30 dias | B14: 284 | C14: 0.1517094 | D14: 62 | E14: 0.18618619 | F14: 346 | G14: 0.1569161 | H14: =D14/F14 -> 0.17919075
A15: 31-45 dias | B15: 239 | C15: 0.12767094 | D15: 46 | E15: 0.13813814 | F15: 285 | G15: 0.1292517 | H15: =D15/F15 -> 0.16140351
A16: 46-60 dias | B16: 317 | C16: 0.16933761 | D16: 43 | E16: 0.12912913 | F16: 360 | G16: 0.16326531 | H16: =D16/F16 -> 0.11944444
A17: 61-75 dias | B17: 292 | C17: 0.15598291 | D17: 33 | E17: 0.099099099 | F17: 325 | G17: 0.14739229 | H17: =D17/F17 -> 0.10153846
A18: 76-99 dias | B18: 483 | C18: 0.25801282 | D18: 38 | E18: 0.11411411 | F18: 521 | G18: 0.23628118 | H18: =D18/F18 -> 0.07293666
A19: Total Geral | B19: 1872 | C19: 1 | D19: 333 | E19: 1 | F19: 2205 | G19: 1 | H19: =D19/F19 -> 0.15102041
B22: Aceitou a campanha? | J22: Existem diferenças de aceitação entre estados civis, porém com menor impacto e menor acionabilidade em comparação às variáveis comportamentais.
B23: 0 | D23: 1 | F23: Total Freq. Absoluta | G23: Total Freq. Relativa | J23: Esta variável é útil para contextualizar perfis, mas não deve guiar decisões de envio ISOLADAMENTE.
A24: Estado Civil | B24: Freq. Absoluta | C24: Freq. Relativa | D24: Freq. Absoluta | E24: Freq. Relativa | H24: Aceitou (%) | J24: Estado civil apresenta menor dispersão real de aceitação do que variáveis comportamentais e economicas. Parte da variação vem de volume de dados pequeno (viúvos)
A25: Casado | B25: 756 | C25: 0.40384615 | D25: 98 | E25: 0.29429429 | F25: 854 | G25: 0.38730159 | H25: =D25/F25 -> 0.1147541
A26: Divorciado | B26: 182 | C26: 0.097222222 | D26: 48 | E26: 0.14414414 | F26: 230 | G26: 0.10430839 | H26: =D26/F26 -> 0.20869565
A27: Juntos | B27: 508 | C27: 0.27136752 | D27: 60 | E27: 0.18018018 | F27: 568 | G27: 0.25759637 | H27: =D27/F27 -> 0.1056338
A28: Solteiro | B28: 368 | C28: 0.1965812 | D28: 109 | E28: 0.32732733 | F28: 477 | G28: 0.21632653 | H28: =D28/F28 -> 0.22851153
A29: Viúvo | B29: 58 | C29: 0.030982906 | D29: 18 | E29: 0.054054054 | F29: 76 | G29: 0.03446712 | H29: =D29/F29 -> 0.23684211
A30: Total Geral | B30: 1872 | C30: 1 | D30: 333 | E30: 1 | F30: 2205 | G30: 1 | H30: =D30/F30 -> 0.15102041
B33: Aceitou a campanha? | J33: O canal de compras influencia significativamente a aceitação da campanha, com clientes de canais remotos apresentando maior receptividade a campanha.
B34: 0 | D34: 1 | F34: Total Freq. Absoluta | G34: Total Freq. Relativa
A35: Canal Predominante | B35: Freq. Absoluta | C35: Freq. Relativa | D35: Freq. Absoluta | E35: Freq. Relativa | H35: Aceitou (%)
A36: Catalog | B36: 98 | C36: 0.052350427 | D36: 57 | E36: 0.17117117 | F36: 155 | G36: 0.070294785 | H36: =D36/F36 -> 0.36774194
A37: Web | B37: 466 | C37: 0.24893162 | D37: 126 | E37: 0.37837838 | F37: 592 | G37: 0.26848073 | H37: =D37/F37 -> 0.21283784
A38: Store | B38: 1308 | C38: 0.69871795 | D38: 150 | E38: 0.45045045 | F38: 1458 | G38: 0.66122449 | H38: =D38/F38 -> 0.10288066
A39: Total Geral | B39: 1872 | C39: 1 | D39: 333 | E39: 1 | F39: 2205 | G39: 1 | H39: =D39/F39 -> 0.15102041
B42: Aceitou a campanha? | J42: Clientes com ticket médio elevado apresentam propensão significativamente maior à aceitação da campanha, indicando maior abertura a ofertas de maior valor.
B43: 0 | D43: 1 | F43: Total Freq. Absoluta | G43: Total Freq. Relativa
A44: Ticket Médio | B44: Freq. Absoluta | C44: Freq. Relativa | D44: Freq. Absoluta | E44: Freq. Relativa | H44: Aceitou (%)
A45: R$ 1–25 | B45: 948 | C45: 0.50641026 | D45: 99 | E45: 0.2972973 | F45: 1047 | G45: 0.47482993 | H45: =D45/F45 -> 0.094555874
A46: R$ 26–50 | B46: 544 | C46: 0.29059829 | D46: 77 | E46: 0.23123123 | F46: 621 | G46: 0.28163265 | H46: =D46/F46 -> 0.12399356
A47: +R$ 50 | B47: 380 | C47: 0.20299145 | D47: 157 | E47: 0.47147147 | F47: 537 | G47: 0.24353741 | H47: =D47/F47 -> 0.29236499
A48: Total Geral | B48: 1872 | C48: 1 | D48: 333 | E48: 1 | F48: 2205 | G48: 1 | H48: =D48/F48 -> 0.15102041
B52: Aceitou a campanha? | J52: O valor histórico acumulado gasto pelo cliente é fortemente associado à aceitação da campanha. Há um crescimento expressivo conforme o valor gasto aumenta.
B53: 0 | D53: 1 | F53: Total Freq. Absoluta | G53: Total Freq. Relativa
A54: Total Gasto Pelo Cliente | B54: Freq. Absoluta | C54: Freq. Relativa | D54: Freq. Absoluta | E54: Freq. Relativa | H54: Aceitou (%)
A55: R$ 0-100 | B55: 693 | C55: 0.37019231 | D55: 61 | E55: 0.18318318 | F55: 754 | G55: 0.34195011 | H55: =D55/F55 -> 0.080901857
A56: R$ 101-500 | B56: 455 | C56: 0.24305556 | D56: 67 | E56: 0.2012012 | F56: 522 | G56: 0.23673469 | H56: =D56/F56 -> 0.12835249
A57: R$ 501-1000 | B57: 363 | C57: 0.19391026 | D57: 42 | E57: 0.12612613 | F57: 405 | G57: 0.18367347 | H57: =D57/F57 -> 0.1037037
A58: R$ 1001-1500 | B58: 253 | C58: 0.13514957 | D58: 74 | E58: 0.22222222 | F58: 327 | G58: 0.14829932 | H58: =D58/F58 -> 0.22629969
A59: +R$ 1500 | B59: 108 | C59: 0.057692308 | D59: 89 | E59: 0.26726727 | F59: 197 | G59: 0.089342404 | H59: =D59/F59 -> 0.45177665
A60: Total Geral | B60: 1872 | C60: 1 | D60: 333 | E60: 1 | F60: 2205 | G60: 1 | H60: =D60/F60 -> 0.15102041
A65: Insight Geral:
A66: A aceitação da campanha é majoritariamente explicada por variáveis comportamentais e econômicas — especialmente recência, valor histórico e ticket médio — que apresentam padrões consistentes, monotônicos e altamente interpretáveis.
A67: Variáveis demográficas possuem papel secundário e explicativo, mas não decisório.

Sheet ROI
A1: Cálculo do ROI para estratégia proposta.
A3: Segmentação (Recência | Gasto Total | Ticket Médio) | B3: Clientes contactados | C3: Quantos aceitaram? | D3: Média aceitação | F3: Segmentação (Recência | Gasto Total | Ticket Médio) | G3: Receita Esperada (R$) | H3: Custo Campanha (R$) | I3: Lucro Esperado (R$) | J3: Decisão | L3: Dados Primários: | O3: Dados Secundários:
A4: 0-15 dias | +R$ 1500 | +R$ 50 | B4: 31 | C4: 19 | D4: 0.61290323 | F4: 0-15 dias | +R$ 1500 | +R$ 50 | G4: 207.75595 | H4: 93 | I4: 114.75595 | J4: Enviar campanha | L4: Clientes da campanha piloto: | M4: 2240 | O4: Custo por contato: | P4: =M5/M4 -> 3 | Q4: por cliente
A5: 0-15 dias | R$ 0-100 | R$ 1–25 | B5: 127 | C5: 28 | D5: 0.22047244 | F5: 76-99 dias | R$ 1001-1500 | R$ 26–50 | G5: 196.82143 | H5: 90 | I5: 106.82143 | J5: Enviar campanha | L5: Custo total da campanha: | M5: 6720 | O5: Qtd. Clientes que aceitaram: | P5: =M4*M7 -> 336 | Q5: clientes
A6: 0-15 dias | R$ 0-100 | R$ 26–50 | B6: 1 | C6: 0 | D6: 0 | F6: 61-75 dias | +R$ 1500 | +R$ 50 | G6: 218.69048 | H6: 126 | I6: 92.690476 | J6: Enviar campanha | L6: Receita total gerada: | M6: 3674 | O6: Receita unitária por cada cliente | P6: =M6/P5 -> 10.934524 | Q6: por cliente
A7: 0-15 dias | R$ 1001-1500 | +R$ 50 | B7: 42 | C7: 20 | D7: 0.47619048 | F7: 46-60 dias | R$ 101-500 | R$ 26–50 | G7: 164.01786 | H7: 87 | I7: 77.017857 | J7: Enviar campanha | L7: Taxa de sucesso (aceitação) | M7: 0.15
A8: 0-15 dias | R$ 1001-1500 | R$ 26–50 | B8: 12 | C8: 2 | D8: 0.16666667 | F8: 0-15 dias | R$ 501-1000 | +R$ 50 | G8: 153.08333 | H8: 84 | I8: 69.083333 | J8: Enviar campanha | L8: Lucro campanha piloto: | M8: =M6-M5 -> -3046
A9: 0-15 dias | R$ 101-500 | +R$ 50 | B9: 1 | C9: 0 | D9: 0 | F9: 31-45 dias | R$ 501-1000 | +R$ 50 | G9: 109.34524 | H9: 72 | I9: 37.345238 | J9: Enviar campanha
A10: 0-15 dias | R$ 101-500 | R$ 1–25 | B10: 52 | C10: 14 | D10: 0.26923077 | F10: 16-30 dias | R$ 1001-1500 | +R$ 50 | G10: 142.14881 | H10: 114 | I10: 28.14881 | J10: Enviar campanha
A11: 0-15 dias | R$ 101-500 | R$ 26–50 | B11: 38 | C11: 13 | D11: 0.34210526 | F11: 0-15 dias | R$ 101-500 | +R$ 50 | G11: 153.08333 | H11: 132 | I11: 21.083333 | J11: Enviar campanha
A12: 0-15 dias | R$ 501-1000 | +R$ 50 | B12: 7 | C12: 2 | D12: 0.28571429 | F12: 16-30 dias | R$ 501-1000 | R$ 26–50 | G12: 21.869048 | H12: 6 | I12: 15.869048 | J12: Enviar campanha
A13: 0-15 dias | R$ 501-1000 | R$ 26–50 | B13: 57 | C13: 13 | D13: 0.22807018 | F13: 46-60 dias | R$ 0-100 | +R$ 50 | G13: 32.803571 | H13: 27 | I13: 5.8035714 | J13: Enviar campanha
A14: 16-30 dias | +R$ 1500 | +R$ 50 | B14: 28 | C14: 14 | D14: 0.5 | F14: 76-99 dias | +R$ 1500 | R$ 26–50 | G14: 21.869048 | H14: 21 | I14: 0.86904762 | J14: Enviar campanha
A15: 16-30 dias | R$ 0-100 | +R$ 50 | B15: 2 | C15: 0 | D15: 0 | F15: 0-15 dias | R$ 101-500 | R$ 26–50 | G15: 153.08333 | H15: 156 | I15: -2.9166667 | J15: Não enviar campanha
A16: 16-30 dias | R$ 0-100 | R$ 1–25 | B16: 108 | C16: 12 | D16: 0.11111111 | F16: 0-15 dias | R$ 1001-1500 | +R$ 50 | G16: 0 | H16: 3 | I16: -3 | J16: Não enviar campanha
A17: 16-30 dias | R$ 1001-1500 | +R$ 50 | B17: 44 | C17: 14 | D17: 0.31818182 | F17: 46-60 dias | +R$ 1500 | +R$ 50 | G17: 0 | H17: 3 | I17: -3 | J17: Não enviar campanha
A18: 16-30 dias | R$ 1001-1500 | R$ 26–50 | B18: 9 | C18: 3 | D18: 0.33333333 | F18: 0-15 dias | R$ 501-1000 | R$ 26–50 | G18: 0 | H18: 3 | I18: -3 | J18: Não enviar campanha
A19: 16-30 dias | R$ 101-500 | R$ 1–25 | B19: 53 | C19: 7 | D19: 0.13207547 | F19: 76-99 dias | R$ 1001-1500 | +R$ 50 | G19: 0 | H19: 3 | I19: -3 | J19: Não enviar campanha
A20: 16-30 dias | R$ 101-500 | R$ 26–50 | B20: 34 | C20: 4 | D20: 0.11764706 | F20: 0-15 dias | R$ 0-100 | R$ 1–25 | G20: 0 | H20: 3 | I20: -3 | J20: Não enviar campanha
... A60: 76-99 dias | R$ 501-1000 | R$ 26–50 | B60: 79 | C60: 3 | D60: 0.037974684 | F60: 61-75 dias | R$ 101-500 | R$ 1–25 | G60: 21.869048 | H60: 570 | I60: -548.13095 | J60: Não enviar campanha
A61: Total Geral | B61: 2205 | C61: 333 | D61: 0.15102041
I63: Lucro pós estratégia proposta: | J63: =SUM(I4:I14) -> 569.4881
A65: Canal predominante
A67: Segmento Lucrativo | B67: SIM
A69: Canal | B69: Clientes contactados | C69: Quantos aceitaram? | D69: Média de aceitação | F69: Canal | G69: Receita Esperada (R$) | H69: Custo Campanha (R$) | I69: Lucro Esperado (R$)
A70: Catalog | B70: 46 | C70: 27 | D70: 0.58695652 | F70: Catalog | G70: 295.23214 | H70: 138 | I70: 157.23214
A71: Store | B71: 142 | C71: 44 | D71: 0.30985915 | F71: Store | G71: 295.23214 | H71: 138 | I71: 157.23214
A72: Web | B72: 46 | C72: 27 | D72: 0.58695652 | F72: Web | G72: 481.11905 | H72: 426 | I72: 55.119048
A73: Total Geral | B73: 234 | C73: 98 | D73: 0.41880342
